Workbook
Name Discount: Inputs!$C$28
Name DriverName: Inputs!$B$34:$B$42
Name DriverQty: Inputs!$C$34:$C$42
Name MarginFloor: Inputs!$C$27
Name MarginLever: Inputs!$C$26
Name Months: Inputs!$C$16
Name MonVisits: Inputs!$C$21
Name MonVisitsPerSite: Inputs!$C$17
Name Patients: Inputs!$C$14
Name SiteMonths: Inputs!$C$22
Name Sites: Inputs!$C$13
Name TotalVisits: Inputs!$C$20
Name VisitsPerPatient: Inputs!$C$15
Name Weeks: Inputs!$C$23

Sheet Inputs
B2: PriceDeskLY
B3: Study pricing model - all amounts in INR
B5: HOW TO USE
B6: - Blue cells are yours to edit. Black cells are formulas - do not overwrite them.
B7: - Set the study drivers and commercial levers below, then mark lines with "x" in column A of the Quote sheet.
B8: - Margin is applied line by line, then summed. It is a share of the invoice, not a mark-up on cost.
B9: - Pass-through and Tech lines bill at cost: no margin, no discount, excluded from revenue.
B10: - Summary shows the roll-up. Checks must all read OK before the quote goes out.
B12: STUDY DRIVERS
B13: Sites | C13: 5
B14: Patients enrolled | C14: 250
B15: Visits per patient | C15: 3
B16: Study duration (months) | C16: 12
B17: Monitoring visits per site | C17: 4
B19: DERIVED
B20: Total patient visits | C20: =Patients*VisitsPerPatient -> 750
B21: Total monitoring visits | C21: =Sites*MonVisitsPerSite -> 20
B22: Site-months | C22: =Sites*Months -> 60
B23: Weeks | C23: =ROUND(Months*4.345,0) -> 52
B25: COMMERCIAL LEVERS
B26: Margin on invoice | C26: 0.225 | D26: share of the invoice, not a mark-up on cost
B27: Margin floor (policy) | C27: 0.225 | D27: 22.5% minimum on every sale
B28: Client discount | C28: 0 | D28: applies to professional fees only, never to pass-through
B29: Margin needed for this discount | C29: =1-(1-MarginFloor)*(1-Discount) -> 0.225 | D29: set Margin on invoice to at least this to hold the floor
B32: DRIVER TO QUANTITY | D32: the Quote sheet looks quantities up here
B33: Driver | C33: Quantity
B34: Fixed | C34: =1 -> 1
B35: Per site | C35: =Sites -> 5
B36: Per visit | C36: =TotalVisits -> 750
B37: Per month | C37: =Months -> 12
B38: Per site-month | C38: =SiteMonths -> 60
B39: Per week | C39: =Weeks -> 52
B40: Per monitoring visit | C40: =MonVisits -> 20
B41: Per patient | C41: =Patients -> 250
B42: Manual | C42: =1 -> 1

Sheet Rate Card
A1: Department | B1: Task | C1: Kind | D1: Driver | E1: Delivery hrs | F1: Delivery rate | G1: Review hrs | H1: Review rate | I1: Unit cost | J1: Rate set?
A2: Medical | B2: Concept Note Writing | C2: Service | D2: Fixed | E2: 16 | F2: 950 | G2: 5 | H2: 3000 | I2: =IFERROR(N(E2)*N(F2)+N(G2)*N(H2),0) -> 30200 | J2: =IF(N(I2)>0,"OK","RATE NOT SET") -> OK
A3: Medical | B3: Literature Review/Search (Can vary based on Scope and extent of data) | C3: Service | D3: Fixed | E3: 24 | F3: 950 | G3: 4 | H3: 3000 | I3: =IFERROR(N(E3)*N(F3)+N(G3)*N(H3),0) -> 34800 | J3: =IF(N(I3)>0,"OK","RATE NOT SET") -> OK
A4: Medical | B4: Protocol Writing -Post Marketing/RWE | C4: Service | D4: Fixed | E4: 70 | F4: 950 | G4: 18 | H4: 3000 | I4: =IFERROR(N(E4)*N(F4)+N(G4)*N(H4),0) -> 120500 | J4: =IF(N(I4)>0,"OK","RATE NOT SET") -> OK
A5: Medical | B5: Protocol Writing -Phase 4 | C5: Service | D5: Fixed | E5: 70 | F5: 950 | G5: 18 | H5: 3000 | I5: =IFERROR(N(E5)*N(F5)+N(G5)*N(H5),0) -> 120500 | J5: =IF(N(I5)>0,"OK","RATE NOT SET") -> OK
A6: Medical | B6: ICD (n=1; English) | C6: Service | D6: Fixed | E6: 18 | F6: 950 | G6: 4 | H6: 3000 | I6: =IFERROR(N(E6)*N(F6)+N(G6)*N(H6),0) -> 29100 | J6: =IF(N(I6)>0,"OK","RATE NOT SET") -> OK
A7: Medical | B7: ICD + Ascent (n=1; English) | C7: Service | D7: Fixed | E7: 19 | F7: 950 | G7: 4.25 | H7: 3000 | I7: =IFERROR(N(E7)*N(F7)+N(G7)*N(H7),0) -> 30800 | J7: =IF(N(I7)>0,"OK","RATE NOT SET") -> OK
A8: Medical | B8: Data variable enlisting for DCF/CRF preparation | C8: Service | D8: Fixed | E8: 6 | F8: 950 | G8: 1 | H8: 3000 | I8: =IFERROR(N(E8)*N(F8)+N(G8)*N(H8),0) -> 8700 | J8: =IF(N(I8)>0,"OK","RATE NOT SET") -> OK
A9: Medical | B9: Site Feasibility Questionnaire (Post Concept Finalization) | C9: Service | D9: Fixed | E9: 3.5 | F9: 950 | G9: 1 | H9: 3000 | I9: =IFERROR(N(E9)*N(F9)+N(G9)*N(H9),0) -> 6325 | J9: =IF(N(I9)>0,"OK","RATE NOT SET") -> OK
A10: Medical | B10: Feasibility Questionnaire (e.g. Study Feasibility/Survey) | C10: Service | D10: Fixed | E10: 3.5 | F10: 950 | G10: 2 | H10: 3000 | I10: =IFERROR(N(E10)*N(F10)+N(G10)*N(H10),0) -> 9325 | J10: =IF(N(I10)>0,"OK","RATE NOT SET") -> OK
A11: Medical | B11: Investigator meeting deck | C11: Service | D11: Fixed | E11: 7 | F11: 950 | G11: 4 | H11: 3000 | I11: =IFERROR(N(E11)*N(F11)+N(G11)*N(H11),0) -> 18650 | J11: =IF(N(I11)>0,"OK","RATE NOT SET") -> OK
A12: Medical | B12: Protocol Training Deck | C12: Service | D12: Fixed | E12: 12 | F12: 950 | G12: 3 | H12: 3000 | I12: =IFERROR(N(E12)*N(F12)+N(G12)*N(H12),0) -> 20400 | J12: =IF(N(I12)>0,"OK","RATE NOT SET") -> OK
A13: Medical | B13: SAP - Dummy tables (overlaps with stats) | C13: Service | D13: Fixed | E13: 12 | F13: 950 | G13: 4 | H13: 3000 | I13: =IFERROR(N(E13)*N(F13)+N(G13)*N(H13),0) -> 23400 | J13: =IF(N(I13)>0,"OK","RATE NOT SET") -> OK
A14: Medical | B14: SAR (overlaps with stats) (review, varies as per study depth) | C14: Service | D14: Fixed | F14: 950 | G14: 24 | H14: 3000 | I14: =IFERROR(N(E14)*N(F14)+N(G14)*N(H14),0) -> 72000 | J14: =IF(N(I14)>0,"OK","RATE NOT SET") -> OK
A15: Medical | B15: Statistical Analysis (Varies based on quantum and variables) (review) | C15: Service | D15: Fixed | F15: 950 | G15: 16 | H15: 3000 | I15: =IFERROR(N(E15)*N(F15)+N(G15)*N(H15),0) -> 48000 | J15: =IF(N(I15)>0,"OK","RATE NOT SET") -> OK
A16: Medical | B16: Slide Deck (25 slides; Can vary based on Objective; includes RFP deck, interim report etc.) | C16: Service | D16: Fixed | E16: 28 | F16: 950 | G16: 8 | H16: 3000 | I16: =IFERROR(N(E16)*N(F16)+N(G16)*N(H16),0) -> 50600 | J16: =IF(N(I16)>0,"OK","RATE NOT SET") -> OK
A17: Medical | B17: CSR | C17: Service | D17: Fixed | E17: 28 | F17: 950 | G17: 28 | H17: 3000 | I17: =IFERROR(N(E17)*N(F17)+N(G17)*N(H17),0) -> 110600 | J17: =IF(N(I17)>0,"OK","RATE NOT SET") -> OK
A18: Medical | B18: Journal Selection and list development | C18: Service | D18: Fixed | E18: 8 | F18: 950 | G18: 1.5 | H18: 3000 | I18: =IFERROR(N(E18)*N(F18)+N(G18)*N(H18),0) -> 12100 | J18: =IF(N(I18)>0,"OK","RATE NOT SET") -> OK
A19: Medical | B19: MS writing (Original article for clinical studies) | C19: Service | D19: Fixed | E19: 80 | F19: 950 | G19: 24 | H19: 3000 | I19: =IFERROR(N(E19)*N(F19)+N(G19)*N(H19),0) -> 148000 | J19: =IF(N(I19)>0,"OK","RATE NOT SET") -> OK
A20: Medical | B20: MS writing - Review article (Narrative/SLR) (including literature search and finalization) | C20: Service | D20: Fixed | E20: 80 | F20: 950 | G20: 35 | H20: 3000 | I20: =IFERROR(N(E20)*N(F20)+N(G20)*N(H20),0) -> 181000 | J20: =IF(N(I20)>0,"OK","RATE NOT SET") -> OK
A21: Medical | B21: Abstract for Conference (1st draft for Client's review and approval) | C21: Service | D21: Fixed | E21: 110 | F21: 950 | G21: 5 | H21: 3000 | I21: =IFERROR(N(E21)*N(F21)+N(G21)*N(H21),0) -> 119500 | J21: =IF(N(I21)>0,"OK","RATE NOT SET") -> OK
A22: Medical | B22: Poster in ppt format (1st draft for Client's review and approval) | C22: Service | D22: Fixed | E22: 16 | F22: 950 | G22: 10 | H22: 3000 | I22: =IFERROR(N(E22)*N(F22)+N(G22)*N(H22),0) -> 45200 | J22: =IF(N(I22)>0,"OK","RATE NOT SET") -> OK
A23: Medical | B23: Submission package preparation and journal submission (varies as per journal requirement) | C23: Service | D23: Fixed | E23: 35 | F23: 950 | G23: 1 | H23: 3000 | I23: =IFERROR(N(E23)*N(F23)+N(G23)*N(H23),0) -> 36250 | J23: =IF(N(I23)>0,"OK","RATE NOT SET") -> OK
A24: Medical | B24: Minor Revisions of Submitted Manuscript and Re-submission (Reviewer comments post submission) | C24: Service | D24: Fixed | E24: 12 | F24: 950 | G24: 4 | H24: 3000 | I24: =IFERROR(N(E24)*N(F24)+N(G24)*N(H24),0) -> 23400 | J24: =IF(N(I24)>0,"OK","RATE NOT SET") -> OK
A25: Medical | B25: Major Revisions of Submitted Manuscript and Re-submission (Reviewer comments post submission) | C25: Service | D25: Fixed | E25: 40 | F25: 950 | G25: 12 | H25: 3000 | I25: =IFERROR(N(E25)*N(F25)+N(G25)*N(H25),0) -> 74000 | J25: =IF(N(I25)>0,"OK","RATE NOT SET") -> OK
A26: Medical | B26: Other Activities (Grant writing, RFP documents) | C26: Service | D26: Fixed | E26: 40 | F26: 950 | G26: 12 | H26: 3000 | I26: =IFERROR(N(E26)*N(F26)+N(G26)*N(H26),0) -> 74000 | J26: =IF(N(I26)>0,"OK","RATE NOT SET") -> OK
A27: SSU | B27: Site Identification (per site) | C27: Service | D27: Per site | E27: 0.5 | F27: 800 | G27: 0 | H27: 3000 | I27: =IFERROR(N(E27)*N(F27)+N(G27)*N(H27),0) -> 400 | J27: =IF(N(I27)>0,"OK","RATE NOT SET") -> OK
... A47: SSU | B47: ISF Support | C47: Service | D47: Per site | E47: 16 | F47: 800 | G47: 0 | H47: 3000 | I47: =IFERROR(N(E47)*N(F47)+N(G47)*N(H47),0) -> 12800 | J47: =IF(N(I47)>0,"OK","RATE NOT SET") -> OK
A48: SSU | B48: eISF support | C48: Service | D48: Per site | F48: 800 | G48: 0 | H48: 3000 | I48: =IFERROR(N(E48)*N(F48)+N(G48)*N(H48),0) -> 0 | J48: =IF(N(I48)>0,"OK","RATE NOT SET") -> RATE NOT SET
A49: DM | B49: Protocol Training | C49: Service | D49: Fixed | E49: 25 | F49: 850 | G49: 0 | H49: 3000 | I49: =IFERROR(N(E49)*N(F49)+N(G49)*N(H49),0) -> 21250 | J49: =IF(N(I49)>0,"OK","RATE NOT SET") -> OK
A50: DM | B50: DMP development and finalization | C50: Service | D50: Fixed | E50: 50 | F50: 850 | G50: 2 | H50: 3000 | I50: =IFERROR(N(E50)*N(F50)+N(G50)*N(H50),0) -> 48500 | J50: =IF(N(I50)>0,"OK","RATE NOT SET") -> OK
A51: DM | B51: CRF Development (upto 50 pages) | C51: Service | D51: Fixed | E51: 120 | F51: 850 | G51: 0 | H51: 3000 | I51: =IFERROR(N(E51)*N(F51)+N(G51)*N(H51),0) -> 102000 | J51: =IF(N(I51)>0,"OK","RATE NOT SET") -> OK
A52: DM | B52: CRF Finalization | C52: Service | D52: Fixed | E52: 50 | F52: 850 | G52: 1 | H52: 3000 | I52: =IFERROR(N(E52)*N(F52)+N(G52)*N(H52),0) -> 45500 | J52: =IF(N(I52)>0,"OK","RATE NOT SET") -> OK
A53: DM | B53: DCF development (on paper CRF) | C53: Service | D53: Fixed | E53: 40 | F53: 850 | G53: 0 | H53: 3000 | I53: =IFERROR(N(E53)*N(F53)+N(G53)*N(H53),0) -> 34000 | J53: =IF(N(I53)>0,"OK","RATE NOT SET") -> OK
A54: DM | B54: DCF development (no paper CRF) | C54: Service | D54: Fixed | E54: 80 | F54: 850 | G54: 0 | H54: 3000 | I54: =IFERROR(N(E54)*N(F54)+N(G54)*N(H54),0) -> 68000 | J54: =IF(N(I54)>0,"OK","RATE NOT SET") -> OK
A55: DM | B55: EDC finalization | C55: Service | D55: Fixed | E55: 50 | F55: 850 | G55: 0 | H55: 3000 | I55: =IFERROR(N(E55)*N(F55)+N(G55)*N(H55),0) -> 42500 | J55: =IF(N(I55)>0,"OK","RATE NOT SET") -> OK
A56: DM | B56: EDC UAT- Demo | C56: Service | D56: Fixed | E56: 80 | F56: 850 | G56: 0 | H56: 3000 | I56: =IFERROR(N(E56)*N(F56)+N(G56)*N(H56),0) -> 68000 | J56: =IF(N(I56)>0,"OK","RATE NOT SET") -> OK
A57: DM | B57: EDC UAT- Production | C57: Service | D57: Fixed | E57: 5 | F57: 850 | G57: 1 | H57: 3000 | I57: =IFERROR(N(E57)*N(F57)+N(G57)*N(H57),0) -> 7250 | J57: =IF(N(I57)>0,"OK","RATE NOT SET") -> OK
A58: DM | B58: Data Digitization | C58: Service | D58: Per visit | E58: 1 | F58: 850 | G58: 0 | H58: 3000 | I58: =IFERROR(N(E58)*N(F58)+N(G58)*N(H58),0) -> 850 | J58: =IF(N(I58)>0,"OK","RATE NOT SET") -> OK
A59: DM | B59: Trackers update | C59: Service | D59: Per month | E59: 1.5 | F59: 850 | G59: 10 | H59: 3000 | I59: =IFERROR(N(E59)*N(F59)+N(G59)*N(H59),0) -> 31275 | J59: =IF(N(I59)>0,"OK","RATE NOT SET") -> OK
A60: DM | B60: EDC completion guidelines | C60: Service | D60: Fixed | E60: 60 | F60: 850 | G60: 1 | H60: 3000 | I60: =IFERROR(N(E60)*N(F60)+N(G60)*N(H60),0) -> 54000 | J60: =IF(N(I60)>0,"OK","RATE NOT SET") -> OK
... A101: EC | B101: Regulatory updates | C101: Service | D101: Fixed | E101: 5 | F101: 1200 | G101: 0 | H101: 3000 | I101: =IFERROR(N(E101)*N(F101)+N(G101)*N(H101),0) -> 6000 | J101: =IF(N(I101)>0,"OK","RATE NOT SET") -> OK
A102: BioStats | B102: SAP - Dummy tables | C102: Service | D102: Fixed | F102: 1200 | G102: 0 | H102: 3000 | I102: =IFERROR(N(E102)*N(F102)+N(G102)*N(H102),0) -> 0 | J102: =IF(N(I102)>0,"OK","RATE NOT SET") -> RATE NOT SET
A103: BioStats | B103: SAR | C103: Service | D103: Fixed | F103: 1200 | G103: 0 | H103: 3000 | I103: =IFERROR(N(E103)*N(F103)+N(G103)*N(H103),0) -> 0 | J103: =IF(N(I103)>0,"OK","RATE NOT SET") -> RATE NOT SET
A104: BioStats | B104: Analysis | C104: Service | D104: Fixed | F104: 1200 | G104: 0 | H104: 3000 | I104: =IFERROR(N(E104)*N(F104)+N(G104)*N(H104),0) -> 0 | J104: =IF(N(I104)>0,"OK","RATE NOT SET") -> RATE NOT SET
A105: BioStats | B105: Medical writing Liasion | C105: Service | D105: Fixed | F105: 1200 | G105: 0 | H105: 3000 | I105: =IFERROR(N(E105)*N(F105)+N(G105)*N(H105),0) -> 0 | J105: =IF(N(I105)>0,"OK","RATE NOT SET") -> RATE NOT SET
A106: PTC | B106: ICD Translation & back translations | C106: Pass-through | D106: Manual | I106: 20000 | J106: =IF(N(I106)>0,"OK","RATE NOT SET") -> OK
A107: PTC | B107: Ethics Committee Fee - Institutional | C107: Pass-through | D107: Per site | I107: 100000 | J107: =IF(N(I107)>0,"OK","RATE NOT SET") -> OK
A108: PTC | B108: Ethics Committee Fee - Central | C108: Pass-through | D108: Per site | I108: 20000 | J108: =IF(N(I108)>0,"OK","RATE NOT SET") -> OK
A109: PTC | B109: Travel - Local | C109: Pass-through | D109: Manual | I109: 2500 | J109: =IF(N(I109)>0,"OK","RATE NOT SET") -> OK
A110: PTC | B110: Travel - Out of Station | C110: Pass-through | D110: Manual | I110: 20000 | J110: =IF(N(I110)>0,"OK","RATE NOT SET") -> OK
A111: PTC | B111: Boarding & lodging | C111: Pass-through | D111: Manual | I111: 10000 | J111: =IF(N(I111)>0,"OK","RATE NOT SET") -> OK
A112: PTC | B112: Printing & Courier | C112: Pass-through | D112: Manual | I112: 2000 | J112: =IF(N(I112)>0,"OK","RATE NOT SET") -> OK
A113: PTC | B113: External CRC | C113: Pass-through | D113: Per site-month | I113: 30000 | J113: =IF(N(I113)>0,"OK","RATE NOT SET") -> OK
A114: PTC | B114: External Data entry operator | C114: Pass-through | D114: Manual | I114: 20000 | J114: =IF(N(I114)>0,"OK","RATE NOT SET") -> OK
A115: PTC | B115: Journal Fee | C115: Pass-through | D115: Fixed | J115: =IF(N(I115)>0,"OK","RATE NOT SET") -> RATE NOT SET
A116: PTC | B116: PI Fee / Data record Fee (per patient) | C116: Pass-through | D116: Per patient | I116: 4000 | J116: =IF(N(I116)>0,"OK","RATE NOT SET") -> OK
A117: PTC | B117: Data entry Fee (per patient) | C117: Pass-through | D117: Per patient | J117: =IF(N(I117)>0,"OK","RATE NOT SET") -> RATE NOT SET
A118: PTC | B118: Institutional Overhead | C118: Pass-through | D118: Per site | J118: =IF(N(I118)>0,"OK","RATE NOT SET") -> RATE NOT SET
A119: Tech | B119: EDC Monthly License Fee | C119: Pass-through | D119: Per month | J119: =IF(N(I119)>0,"OK","RATE NOT SET") -> RATE NOT SET
A120: Tech | B120: MEDDRA License Fee | C120: Pass-through | D120: Fixed | J120: =IF(N(I120)>0,"OK","RATE NOT SET") -> RATE NOT SET
A121: Tech | B121: QoL/PRO License Fee | C121: Pass-through | D121: Fixed | J121: =IF(N(I121)>0,"OK","RATE NOT SET") -> RATE NOT SET
A122: Tech | B122: eTMF monthly license Fee | C122: Pass-through | D122: Per month | J122: =IF(N(I122)>0,"OK","RATE NOT SET") -> RATE NOT SET
A123: Tech | B123: eISF monthly license Fee | C123: Pass-through | D123: Per month | J123: =IF(N(I123)>0,"OK","RATE NOT SET") -> RATE NOT SET
B125: Delivery rate = department hourly cost. Review rate = INR 3,000/hr senior review.
B126: Source: client rate card supplied 20 Aug 2026. Blank hours mean the rate was never set - fill them in.

Sheet Summary
B2: Quote summary
B3: Every figure below is a roll-up of the Quote sheet. Nothing is typed here.
B5: Lines included | C5: =COUNTIF(Quote!$A$2:$A$123,"x") -> 33
B6: Total fixed fee (cost) | C6: =SUMIFS(Quote!$L$2:$L$123,Quote!$D$2:$D$123,"Service") -> 3806350 | D6: sum of Line cost on service lines
B7: Sum of line prices | C7: =SUMIFS(Quote!$K$2:$K$123,Quote!$D$2:$D$123,"Service") -> 4912119 | D7: sum of Line price - margin already inside each line
B8: Margin (rupees) | C8: =C7-C6 -> 1105769 | D8: the difference, not a separate uplift
B9: Discount | C9: =-C7*Discount -> 0 | D9: professional fees only
B10: Net revenue | C10: =C7+C9 -> 4912119 | D10: what you actually earn
B11: Pass-through at cost | C11: =SUMIFS(Quote!$L$2:$L$123,Quote!$D$2:$D$123,"Pass-through") -> 100000 | D11: no margin, no discount, not revenue
B12: Client price | C12: =C10+C11 -> 5012119 | D12: total invoice
B13: Margin on revenue | C13: =IF(C10=0,0,(C10-C6)/C10) -> 0.22511039 | D13: must be at or above the floor
B14: Uplift on cost | C14: =IF(C6=0,0,(C7-C6)/C6) -> 0.29050639 | D14: what 22.5% margin looks like as a mark-up
B15: Delivery hours | C15: =SUM(Quote!M2:M123) -> 3984
B16: Review hours | C16: =SUM(Quote!N2:N123) -> 73.5
B19: BY DEPARTMENT
B20: Department | C20: Lines | D20: Cost | E20: Price | F20: Share of price
B21: Medical | C21: =COUNTIFS(Quote!$A$2:$A$123,"x",Quote!$B$2:$B$123,$B21) -> 8 | D21: =SUMIFS(Quote!$L$2:$L$123,Quote!$B$2:$B$123,$B21) -> 360625 | E21: =SUMIFS(Quote!$K$2:$K$123,Quote!$B$2:$B$123,$B21) -> 465323 | F21: =IF($E$30=0,0,E21/$E$30) -> 0.092839575
B22: SSU | C22: =COUNTIFS(Quote!$A$2:$A$123,"x",Quote!$B$2:$B$123,$B22) -> 10 | D22: =SUMIFS(Quote!$L$2:$L$123,Quote!$B$2:$B$123,$B22) -> 133300 | E22: =SUMIFS(Quote!$K$2:$K$123,Quote!$B$2:$B$123,$B22) -> 172005 | F22: =IF($E$30=0,0,E22/$E$30) -> 0.03431782
B23: DM | C23: =COUNTIFS(Quote!$A$2:$A$123,"x",Quote!$B$2:$B$123,$B23) -> 8 | D23: =SUMIFS(Quote!$L$2:$L$123,Quote!$B$2:$B$123,$B23) -> 2794025 | E23: =SUMIFS(Quote!$K$2:$K$123,Quote!$B$2:$B$123,$B23) -> 3605872 | F23: =IF($E$30=0,0,E23/$E$30) -> 0.71943064
B24: PM | C24: =COUNTIFS(Quote!$A$2:$A$123,"x",Quote!$B$2:$B$123,$B24) -> 4 | D24: =SUMIFS(Quote!$L$2:$L$123,Quote!$B$2:$B$123,$B24) -> 494400 | E24: =SUMIFS(Quote!$K$2:$K$123,Quote!$B$2:$B$123,$B24) -> 637951 | F24: =IF($E$30=0,0,E24/$E$30) -> 0.12728169
B25: SM | C25: =COUNTIFS(Quote!$A$2:$A$123,"x",Quote!$B$2:$B$123,$B25) -> 0 | D25: =SUMIFS(Quote!$L$2:$L$123,Quote!$B$2:$B$123,$B25) -> 0 | E25: =SUMIFS(Quote!$K$2:$K$123,Quote!$B$2:$B$123,$B25) -> 0 | F25: =IF($E$30=0,0,E25/$E$30) -> 0
B26: EC | C26: =COUNTIFS(Quote!$A$2:$A$123,"x",Quote!$B$2:$B$123,$B26) -> 2 | D26: =SUMIFS(Quote!$L$2:$L$123,Quote!$B$2:$B$123,$B26) -> 24000 | E26: =SUMIFS(Quote!$K$2:$K$123,Quote!$B$2:$B$123,$B26) -> 30968 | F26: =IF($E$30=0,0,E26/$E$30) -> 0.0061786243
B27: BioStats | C27: =COUNTIFS(Quote!$A$2:$A$123,"x",Quote!$B$2:$B$123,$B27) -> 0 | D27: =SUMIFS(Quote!$L$2:$L$123,Quote!$B$2:$B$123,$B27) -> 0 | E27: =SUMIFS(Quote!$K$2:$K$123,Quote!$B$2:$B$123,$B27) -> 0 | F27: =IF($E$30=0,0,E27/$E$30) -> 0
B28: PTC | C28: =COUNTIFS(Quote!$A$2:$A$123,"x",Quote!$B$2:$B$123,$B28) -> 1 | D28: =SUMIFS(Quote!$L$2:$L$123,Quote!$B$2:$B$123,$B28) -> 100000 | E28: =SUMIFS(Quote!$K$2:$K$123,Quote!$B$2:$B$123,$B28) -> 100000 | F28: =IF($E$30=0,0,E28/$E$30) -> 0.019951641
B29: Tech | C29: =COUNTIFS(Quote!$A$2:$A$123,"x",Quote!$B$2:$B$123,$B29) -> 0 | D29: =SUMIFS(Quote!$L$2:$L$123,Quote!$B$2:$B$123,$B29) -> 0 | E29: =SUMIFS(Quote!$K$2:$K$123,Quote!$B$2:$B$123,$B29) -> 0 | F29: =IF($E$30=0,0,E29/$E$30) -> 0
B30: Total | C30: =SUM(C21:C29) -> 33 | D30: =SUM(D21:D29) -> 3906350 | E30: =SUM(E21:E29) -> 5012119

Sheet Checks
B2: Model checks
B3: All must read OK before this quote leaves the building.
B5: # | C5: Check | D5: Result | E5: Status
B6: 1 | C6: Line prices roll up to the quoted fees | D6: =ROUND(SUMIFS(Quote!$K$2:$K$123,Quote!$D$2:$D$123,"Service")-Summary!C7,2) -> 0 | E6: =IF(D6=0,"OK","FAIL") -> OK
B7: 2 | C7: Qty x Unit price = Line price on every row | D7: =SUMPRODUCT(--(ROUND(Quote!$F$2:$F$123*Quote!$J$2:$J$123,2)<>ROUND(Quote!$K$2:$K$123,2))) -> 0 | E7: =IF(D7=0,"OK","FAIL") -> OK
B8: 3 | C8: Realised margin at or above the floor | D8: =Summary!C13-MarginFloor -> 0.00011038515 | E8: =IF(D8>=-0.0005,"OK","FAIL") -> OK
B9: 4 | C9: Margin lever at or above the floor | D9: =MarginLever-MarginFloor -> 0 | E9: =IF(D9>=0,"OK","FAIL") -> OK
B10: 5 | C10: Included lines with no rate set | D10: =COUNTIFS(Quote!$A$2:$A$123,"x",Quote!$G$2:$G$123,0) -> 0 | E10: =IF(D10=0,"OK","FAIL") -> OK
B11: 6 | C11: Included lines resolving to zero quantity | D11: =COUNTIFS(Quote!$A$2:$A$123,"x",Quote!$F$2:$F$123,0) -> 0 | E11: =IF(D11=0,"OK","REVIEW") -> OK
B12: 7 | C12: Line margin overrides below the floor | D12: =SUMPRODUCT(--(Quote!$H$2:$H$123<>""),--(Quote!$H$2:$H$123<MarginFloor)) -> 0 | E12: =IF(D12=0,"OK","FAIL") -> OK
B13: 8 | C13: Pass-through lines carrying margin | D13: =SUMPRODUCT(--(Quote!$D$2:$D$123="Pass-through"),--(Quote!$I$2:$I$123>0)) -> 0 | E13: =IF(D13=0,"OK","FAIL") -> OK
B14: 9 | C14: Lines where margin differs from the lever | D14: =SUMPRODUCT(--(Quote!$A$2:$A$123="x"),--(Quote!$D$2:$D$123="Service"),--(Quote!$I$2:$I$123<>MarginLever)) -> 0 | E14: =IF(D14=0,"OK","REVIEW") -> OK
B15: 10 | C15: Discount leaves margin under the floor | D15: =IF(Summary!C13<MarginFloor-0.0005,1,0) -> 0 | E15: =IF(D15=0,"OK","FAIL") -> OK
C18: Checks 6 and 9 read REVIEW rather than FAIL: both can be legitimate, but must be deliberate.
C19: Contingency is deliberately absent from this model. It plays no part in the calculation.

Sheet Quote
A1: In | B1: Department | C1: Activity | D1: Kind | E1: Driver | F1: Qty | G1: Unit cost | H1: Margin override | I1: Margin applied | J1: Unit price | K1: Line price | L1: Line cost | M1: Delivery hrs | N1: Review hrs
A2: x | B2: ='Rate Card'!A2 -> Medical | C2: ='Rate Card'!B2 -> Concept Note Writing | D2: ='Rate Card'!C2 -> Service | E2: ='Rate Card'!D2 -> Fixed | F2: =IF($A2="x",IFERROR(INDEX(DriverQty,MATCH($E2,DriverName,0)),0),0) -> 1 | G2: ='Rate Card'!I2 -> 30200 | I2: =IF($D2="Pass-through",0,MAX(MarginFloor,IF($H2="",MarginLever,$H2))) -> 0.225 | J2: =IF($D2="Pass-through",$G2,IF($I2>=1,$G2,ROUND($G2/(1-$I2),0))) -> 38968 | K2: =$F2*$J2 -> 38968 | L2: =$F2*$G2 -> 30200 | M2: =$F2*N('Rate Card'!E2) -> 16 | N2: =$F2*N('Rate Card'!G2) -> 5
A3: x | B3: ='Rate Card'!A3 -> Medical | C3: ='Rate Card'!B3 -> Literature Review/Search (Can vary based on Scope and extent of data) | D3: ='Rate Card'!C3 -> Service | E3: ='Rate Card'!D3 -> Fixed | F3: =IF($A3="x",IFERROR(INDEX(DriverQty,MATCH($E3,DriverName,0)),0),0) -> 1 | G3: ='Rate Card'!I3 -> 34800 | I3: =IF($D3="Pass-through",0,MAX(MarginFloor,IF($H3="",MarginLever,$H3))) -> 0.225 | J3: =IF($D3="Pass-through",$G3,IF($I3>=1,$G3,ROUND($G3/(1-$I3),0))) -> 44903 | K3: =$F3*$J3 -> 44903 | L3: =$F3*$G3 -> 34800 | M3: =$F3*N('Rate Card'!E3) -> 24 | N3: =$F3*N('Rate Card'!G3) -> 4
A4: x | B4: ='Rate Card'!A4 -> Medical | C4: ='Rate Card'!B4 -> Protocol Writing -Post Marketing/RWE | D4: ='Rate Card'!C4 -> Service | E4: ='Rate Card'!D4 -> Fixed | F4: =IF($A4="x",IFERROR(INDEX(DriverQty,MATCH($E4,DriverName,0)),0),0) -> 1 | G4: ='Rate Card'!I4 -> 120500 | I4: =IF($D4="Pass-through",0,MAX(MarginFloor,IF($H4="",MarginLever,$H4))) -> 0.225 | J4: =IF($D4="Pass-through",$G4,IF($I4>=1,$G4,ROUND($G4/(1-$I4),0))) -> 155484 | K4: =$F4*$J4 -> 155484 | L4: =$F4*$G4 -> 120500 | M4: =$F4*N('Rate Card'!E4) -> 70 | N4: =$F4*N('Rate Card'!G4) -> 18
B5: ='Rate Card'!A5 -> Medical | C5: ='Rate Card'!B5 -> Protocol Writing -Phase 4 | D5: ='Rate Card'!C5 -> Service | E5: ='Rate Card'!D5 -> Fixed | F5: =IF($A5="x",IFERROR(INDEX(DriverQty,MATCH($E5,DriverName,0)),0),0) -> 0 | G5: ='Rate Card'!I5 -> 120500 | I5: =IF($D5="Pass-through",0,MAX(MarginFloor,IF($H5="",MarginLever,$H5))) -> 0.225 | J5: =IF($D5="Pass-through",$G5,IF($I5>=1,$G5,ROUND($G5/(1-$I5),0))) -> 155484 | K5: =$F5*$J5 -> 0 | L5: =$F5*$G5 -> 0 | M5: =$F5*N('Rate Card'!E5) -> 0 | N5: =$F5*N('Rate Card'!G5) -> 0
A6: x | B6: ='Rate Card'!A6 -> Medical | C6: ='Rate Card'!B6 -> ICD (n=1; English) | D6: ='Rate Card'!C6 -> Service | E6: ='Rate Card'!D6 -> Fixed | F6: =IF($A6="x",IFERROR(INDEX(DriverQty,MATCH($E6,DriverName,0)),0),0) -> 1 | G6: ='Rate Card'!I6 -> 29100 | I6: =IF($D6="Pass-through",0,MAX(MarginFloor,IF($H6="",MarginLever,$H6))) -> 0.225 | J6: =IF($D6="Pass-through",$G6,IF($I6>=1,$G6,ROUND($G6/(1-$I6),0))) -> 37548 | K6: =$F6*$J6 -> 37548 | L6: =$F6*$G6 -> 29100 | M6: =$F6*N('Rate Card'!E6) -> 18 | N6: =$F6*N('Rate Card'!G6) -> 4
B7: ='Rate Card'!A7 -> Medical | C7: ='Rate Card'!B7 -> ICD + Ascent (n=1; English) | D7: ='Rate Card'!C7 -> Service | E7: ='Rate Card'!D7 -> Fixed | F7: =IF($A7="x",IFERROR(INDEX(DriverQty,MATCH($E7,DriverName,0)),0),0) -> 0 | G7: ='Rate Card'!I7 -> 30800 | I7: =IF($D7="Pass-through",0,MAX(MarginFloor,IF($H7="",MarginLever,$H7))) -> 0.225 | J7: =IF($D7="Pass-through",$G7,IF($I7>=1,$G7,ROUND($G7/(1-$I7),0))) -> 39742 | K7: =$F7*$J7 -> 0 | L7: =$F7*$G7 -> 0 | M7: =$F7*N('Rate Card'!E7) -> 0 | N7: =$F7*N('Rate Card'!G7) -> 0
A8: x | B8: ='Rate Card'!A8 -> Medical | C8: ='Rate Card'!B8 -> Data variable enlisting for DCF/CRF preparation | D8: ='Rate Card'!C8 -> Service | E8: ='Rate Card'!D8 -> Fixed | F8: =IF($A8="x",IFERROR(INDEX(DriverQty,MATCH($E8,DriverName,0)),0),0) -> 1 | G8: ='Rate Card'!I8 -> 8700 | I8: =IF($D8="Pass-through",0,MAX(MarginFloor,IF($H8="",MarginLever,$H8))) -> 0.225 | J8: =IF($D8="Pass-through",$G8,IF($I8>=1,$G8,ROUND($G8/(1-$I8),0))) -> 11226 | K8: =$F8*$J8 -> 11226 | L8: =$F8*$G8 -> 8700 | M8: =$F8*N('Rate Card'!E8) -> 6 | N8: =$F8*N('Rate Card'!G8) -> 1
A9: x | B9: ='Rate Card'!A9 -> Medical | C9: ='Rate Card'!B9 -> Site Feasibility Questionnaire (Post Concept Finalization) | D9: ='Rate Card'!C9 -> Service | E9: ='Rate Card'!D9 -> Fixed | F9: =IF($A9="x",IFERROR(INDEX(DriverQty,MATCH($E9,DriverName,0)),0),0) -> 1 | G9: ='Rate Card'!I9 -> 6325 | I9: =IF($D9="Pass-through",0,MAX(MarginFloor,IF($H9="",MarginLever,$H9))) -> 0.225 | J9: =IF($D9="Pass-through",$G9,IF($I9>=1,$G9,ROUND($G9/(1-$I9),0))) -> 8161 | K9: =$F9*$J9 -> 8161 | L9: =$F9*$G9 -> 6325 | M9: =$F9*N('Rate Card'!E9) -> 3.5 | N9: =$F9*N('Rate Card'!G9) -> 1
B10: ='Rate Card'!A10 -> Medical | C10: ='Rate Card'!B10 -> Feasibility Questionnaire (e.g. Study Feasibility/Survey) | D10: ='Rate Card'!C10 -> Service | E10: ='Rate Card'!D10 -> Fixed | F10: =IF($A10="x",IFERROR(INDEX(DriverQty,MATCH($E10,DriverName,0)),0),0) -> 0 | G10: ='Rate Card'!I10 -> 9325 | I10: =IF($D10="Pass-through",0,MAX(MarginFloor,IF($H10="",MarginLever,$H10))) -> 0.225 | J10: =IF($D10="Pass-through",$G10,IF($I10>=1,$G10,ROUND($G10/(1-$I10),0))) -> 12032 | K10: =$F10*$J10 -> 0 | L10: =$F10*$G10 -> 0 | M10: =$F10*N('Rate Card'!E10) -> 0 | N10: =$F10*N('Rate Card'!G10) -> 0
B11: ='Rate Card'!A11 -> Medical | C11: ='Rate Card'!B11 -> Investigator meeting deck | D11: ='Rate Card'!C11 -> Service | E11: ='Rate Card'!D11 -> Fixed | F11: =IF($A11="x",IFERROR(INDEX(DriverQty,MATCH($E11,DriverName,0)),0),0) -> 0 | G11: ='Rate Card'!I11 -> 18650 | I11: =IF($D11="Pass-through",0,MAX(MarginFloor,IF($H11="",MarginLever,$H11))) -> 0.225 | J11: =IF($D11="Pass-through",$G11,IF($I11>=1,$G11,ROUND($G11/(1-$I11),0))) -> 24065 | K11: =$F11*$J11 -> 0 | L11: =$F11*$G11 -> 0 | M11: =$F11*N('Rate Card'!E11) -> 0 | N11: =$F11*N('Rate Card'!G11) -> 0
A12: x | B12: ='Rate Card'!A12 -> Medical | C12: ='Rate Card'!B12 -> Protocol Training Deck | D12: ='Rate Card'!C12 -> Service | E12: ='Rate Card'!D12 -> Fixed | F12: =IF($A12="x",IFERROR(INDEX(DriverQty,MATCH($E12,DriverName,0)),0),0) -> 1 | G12: ='Rate Card'!I12 -> 20400 | I12: =IF($D12="Pass-through",0,MAX(MarginFloor,IF($H12="",MarginLever,$H12))) -> 0.225 | J12: =IF($D12="Pass-through",$G12,IF($I12>=1,$G12,ROUND($G12/(1-$I12),0))) -> 26323 | K12: =$F12*$J12 -> 26323 | L12: =$F12*$G12 -> 20400 | M12: =$F12*N('Rate Card'!E12) -> 12 | N12: =$F12*N('Rate Card'!G12) -> 3
B13: ='Rate Card'!A13 -> Medical | C13: ='Rate Card'!B13 -> SAP - Dummy tables (overlaps with stats) | D13: ='Rate Card'!C13 -> Service | E13: ='Rate Card'!D13 -> Fixed | F13: =IF($A13="x",IFERROR(INDEX(DriverQty,MATCH($E13,DriverName,0)),0),0) -> 0 | G13: ='Rate Card'!I13 -> 23400 | I13: =IF($D13="Pass-through",0,MAX(MarginFloor,IF($H13="",MarginLever,$H13))) -> 0.225 | J13: =IF($D13="Pass-through",$G13,IF($I13>=1,$G13,ROUND($G13/(1-$I13),0))) -> 30194 | K13: =$F13*$J13 -> 0 | L13: =$F13*$G13 -> 0 | M13: =$F13*N('Rate Card'!E13) -> 0 | N13: =$F13*N('Rate Card'!G13) -> 0
B14: ='Rate Card'!A14 -> Medical | C14: ='Rate Card'!B14 -> SAR (overlaps with stats) (review, varies as per study depth) | D14: ='Rate Card'!C14 -> Service | E14: ='Rate Card'!D14 -> Fixed | F14: =IF($A14="x",IFERROR(INDEX(DriverQty,MATCH($E14,DriverName,0)),0),0) -> 0 | G14: ='Rate Card'!I14 -> 72000 | I14: =IF($D14="Pass-through",0,MAX(MarginFloor,IF($H14="",MarginLever,$H14))) -> 0.225 | J14: =IF($D14="Pass-through",$G14,IF($I14>=1,$G14,ROUND($G14/(1-$I14),0))) -> 92903 | K14: =$F14*$J14 -> 0 | L14: =$F14*$G14 -> 0 | M14: =$F14*N('Rate Card'!E14) -> 0 | N14: =$F14*N('Rate Card'!G14) -> 0
B15: ='Rate Card'!A15 -> Medical | C15: ='Rate Card'!B15 -> Statistical Analysis (Varies based on quantum and variables) (review) | D15: ='Rate Card'!C15 -> Service | E15: ='Rate Card'!D15 -> Fixed | F15: =IF($A15="x",IFERROR(INDEX(DriverQty,MATCH($E15,DriverName,0)),0),0) -> 0 | G15: ='Rate Card'!I15 -> 48000 | I15: =IF($D15="Pass-through",0,MAX(MarginFloor,IF($H15="",MarginLever,$H15))) -> 0.225 | J15: =IF($D15="Pass-through",$G15,IF($I15>=1,$G15,ROUND($G15/(1-$I15),0))) -> 61935 | K15: =$F15*$J15 -> 0 | L15: =$F15*$G15 -> 0 | M15: =$F15*N('Rate Card'!E15) -> 0 | N15: =$F15*N('Rate Card'!G15) -> 0
B16: ='Rate Card'!A16 -> Medical | C16: ='Rate Card'!B16 -> Slide Deck (25 slides; Can vary based on Objective; includes RFP deck, interim report etc.) | D16: ='Rate Card'!C16 -> Service | E16: ='Rate Card'!D16 -> Fixed | F16: =IF($A16="x",IFERROR(INDEX(DriverQty,MATCH($E16,DriverName,0)),0),0) -> 0 | G16: ='Rate Card'!I16 -> 50600 | I16: =IF($D16="Pass-through",0,MAX(MarginFloor,IF($H16="",MarginLever,$H16))) -> 0.225 | J16: =IF($D16="Pass-through",$G16,IF($I16>=1,$G16,ROUND($G16/(1-$I16),0))) -> 65290 | K16: =$F16*$J16 -> 0 | L16: =$F16*$G16 -> 0 | M16: =$F16*N('Rate Card'!E16) -> 0 | N16: =$F16*N('Rate Card'!G16) -> 0
A17: x | B17: ='Rate Card'!A17 -> Medical | C17: ='Rate Card'!B17 -> CSR | D17: ='Rate Card'!C17 -> Service | E17: ='Rate Card'!D17 -> Fixed | F17: =IF($A17="x",IFERROR(INDEX(DriverQty,MATCH($E17,DriverName,0)),0),0) -> 1 | G17: ='Rate Card'!I17 -> 110600 | I17: =IF($D17="Pass-through",0,MAX(MarginFloor,IF($H17="",MarginLever,$H17))) -> 0.225 | J17: =IF($D17="Pass-through",$G17,IF($I17>=1,$G17,ROUND($G17/(1-$I17),0))) -> 142710 | K17: =$F17*$J17 -> 142710 | L17: =$F17*$G17 -> 110600 | M17: =$F17*N('Rate Card'!E17) -> 28 | N17: =$F17*N('Rate Card'!G17) -> 28
B18: ='Rate Card'!A18 -> Medical | C18: ='Rate Card'!B18 -> Journal Selection and list development | D18: ='Rate Card'!C18 -> Service | E18: ='Rate Card'!D18 -> Fixed | F18: =IF($A18="x",IFERROR(INDEX(DriverQty,MATCH($E18,DriverName,0)),0),0) -> 0 | G18: ='Rate Card'!I18 -> 12100 | I18: =IF($D18="Pass-through",0,MAX(MarginFloor,IF($H18="",MarginLever,$H18))) -> 0.225 | J18: =IF($D18="Pass-through",$G18,IF($I18>=1,$G18,ROUND($G18/(1-$I18),0))) -> 15613 | K18: =$F18*$J18 -> 0 | L18: =$F18*$G18 -> 0 | M18: =$F18*N('Rate Card'!E18) -> 0 | N18: =$F18*N('Rate Card'!G18) -> 0
B19: ='Rate Card'!A19 -> Medical | C19: ='Rate Card'!B19 -> MS writing (Original article for clinical studies) | D19: ='Rate Card'!C19 -> Service | E19: ='Rate Card'!D19 -> Fixed | F19: =IF($A19="x",IFERROR(INDEX(DriverQty,MATCH($E19,DriverName,0)),0),0) -> 0 | G19: ='Rate Card'!I19 -> 148000 | I19: =IF($D19="Pass-through",0,MAX(MarginFloor,IF($H19="",MarginLever,$H19))) -> 0.225 | J19: =IF($D19="Pass-through",$G19,IF($I19>=1,$G19,ROUND($G19/(1-$I19),0))) -> 190968 | K19: =$F19*$J19 -> 0 | L19: =$F19*$G19 -> 0 | M19: =$F19*N('Rate Card'!E19) -> 0 | N19: =$F19*N('Rate Card'!G19) -> 0
B20: ='Rate Card'!A20 -> Medical | C20: ='Rate Card'!B20 -> MS writing - Review article (Narrative/SLR) (including literature search and finalization) | D20: ='Rate Card'!C20 -> Service | E20: ='Rate Card'!D20 -> Fixed | F20: =IF($A20="x",IFERROR(INDEX(DriverQty,MATCH($E20,DriverName,0)),0),0) -> 0 | G20: ='Rate Card'!I20 -> 181000 | I20: =IF($D20="Pass-through",0,MAX(MarginFloor,IF($H20="",MarginLever,$H20))) -> 0.225 | J20: =IF($D20="Pass-through",$G20,IF($I20>=1,$G20,ROUND($G20/(1-$I20),0))) -> 233548 | K20: =$F20*$J20 -> 0 | L20: =$F20*$G20 -> 0 | M20: =$F20*N('Rate Card'!E20) -> 0 | N20: =$F20*N('Rate Card'!G20) -> 0
B21: ='Rate Card'!A21 -> Medical | C21: ='Rate Card'!B21 -> Abstract for Conference (1st draft for Client's review and approval) | D21: ='Rate Card'!C21 -> Service | E21: ='Rate Card'!D21 -> Fixed | F21: =IF($A21="x",IFERROR(INDEX(DriverQty,MATCH($E21,DriverName,0)),0),0) -> 0 | G21: ='Rate Card'!I21 -> 119500 | I21: =IF($D21="Pass-through",0,MAX(MarginFloor,IF($H21="",MarginLever,$H21))) -> 0.225 | J21: =IF($D21="Pass-through",$G21,IF($I21>=1,$G21,ROUND($G21/(1-$I21),0))) -> 154194 | K21: =$F21*$J21 -> 0 | L21: =$F21*$G21 -> 0 | M21: =$F21*N('Rate Card'!E21) -> 0 | N21: =$F21*N('Rate Card'!G21) -> 0
B22: ='Rate Card'!A22 -> Medical | C22: ='Rate Card'!B22 -> Poster in ppt format (1st draft for Client's review and approval) | D22: ='Rate Card'!C22 -> Service | E22: ='Rate Card'!D22 -> Fixed | F22: =IF($A22="x",IFERROR(INDEX(DriverQty,MATCH($E22,DriverName,0)),0),0) -> 0 | G22: ='Rate Card'!I22 -> 45200 | I22: =IF($D22="Pass-through",0,MAX(MarginFloor,IF($H22="",MarginLever,$H22))) -> 0.225 | J22: =IF($D22="Pass-through",$G22,IF($I22>=1,$G22,ROUND($G22/(1-$I22),0))) -> 58323 | K22: =$F22*$J22 -> 0 | L22: =$F22*$G22 -> 0 | M22: =$F22*N('Rate Card'!E22) -> 0 | N22: =$F22*N('Rate Card'!G22) -> 0
B23: ='Rate Card'!A23 -> Medical | C23: ='Rate Card'!B23 -> Submission package preparation and journal submission (varies as per journal requirement) | D23: ='Rate Card'!C23 -> Service | E23: ='Rate Card'!D23 -> Fixed | F23: =IF($A23="x",IFERROR(INDEX(DriverQty,MATCH($E23,DriverName,0)),0),0) -> 0 | G23: ='Rate Card'!I23 -> 36250 | I23: =IF($D23="Pass-through",0,MAX(MarginFloor,IF($H23="",MarginLever,$H23))) -> 0.225 | J23: =IF($D23="Pass-through",$G23,IF($I23>=1,$G23,ROUND($G23/(1-$I23),0))) -> 46774 | K23: =$F23*$J23 -> 0 | L23: =$F23*$G23 -> 0 | M23: =$F23*N('Rate Card'!E23) -> 0 | N23: =$F23*N('Rate Card'!G23) -> 0
B24: ='Rate Card'!A24 -> Medical | C24: ='Rate Card'!B24 -> Minor Revisions of Submitted Manuscript and Re-submission (Reviewer comments post submission) | D24: ='Rate Card'!C24 -> Service | E24: ='Rate Card'!D24 -> Fixed | F24: =IF($A24="x",IFERROR(INDEX(DriverQty,MATCH($E24,DriverName,0)),0),0) -> 0 | G24: ='Rate Card'!I24 -> 23400 | I24: =IF($D24="Pass-through",0,MAX(MarginFloor,IF($H24="",MarginLever,$H24))) -> 0.225 | J24: =IF($D24="Pass-through",$G24,IF($I24>=1,$G24,ROUND($G24/(1-$I24),0))) -> 30194 | K24: =$F24*$J24 -> 0 | L24: =$F24*$G24 -> 0 | M24: =$F24*N('Rate Card'!E24) -> 0 | N24: =$F24*N('Rate Card'!G24) -> 0
B25: ='Rate Card'!A25 -> Medical | C25: ='Rate Card'!B25 -> Major Revisions of Submitted Manuscript and Re-submission (Reviewer comments post submission) | D25: ='Rate Card'!C25 -> Service | E25: ='Rate Card'!D25 -> Fixed | F25: =IF($A25="x",IFERROR(INDEX(DriverQty,MATCH($E25,DriverName,0)),0),0) -> 0 | G25: ='Rate Card'!I25 -> 74000 | I25: =IF($D25="Pass-through",0,MAX(MarginFloor,IF($H25="",MarginLever,$H25))) -> 0.225 | J25: =IF($D25="Pass-through",$G25,IF($I25>=1,$G25,ROUND($G25/(1-$I25),0))) -> 95484 | K25: =$F25*$J25 -> 0 | L25: =$F25*$G25 -> 0 | M25: =$F25*N('Rate Card'!E25) -> 0 | N25: =$F25*N('Rate Card'!G25) -> 0
B26: ='Rate Card'!A26 -> Medical | C26: ='Rate Card'!B26 -> Other Activities (Grant writing, RFP documents) | D26: ='Rate Card'!C26 -> Service | E26: ='Rate Card'!D26 -> Fixed | F26: =IF($A26="x",IFERROR(INDEX(DriverQty,MATCH($E26,DriverName,0)),0),0) -> 0 | G26: ='Rate Card'!I26 -> 74000 | I26: =IF($D26="Pass-through",0,MAX(MarginFloor,IF($H26="",MarginLever,$H26))) -> 0.225 | J26: =IF($D26="Pass-through",$G26,IF($I26>=1,$G26,ROUND($G26/(1-$I26),0))) -> 95484 | K26: =$F26*$J26 -> 0 | L26: =$F26*$G26 -> 0 | M26: =$F26*N('Rate Card'!E26) -> 0 | N26: =$F26*N('Rate Card'!G26) -> 0
A27: x | B27: ='Rate Card'!A27 -> SSU | C27: ='Rate Card'!B27 -> Site Identification (per site) | D27: ='Rate Card'!C27 -> Service | E27: ='Rate Card'!D27 -> Per site | F27: =IF($A27="x",IFERROR(INDEX(DriverQty,MATCH($E27,DriverName,0)),0),0) -> 5 | G27: ='Rate Card'!I27 -> 400 | I27: =IF($D27="Pass-through",0,MAX(MarginFloor,IF($H27="",MarginLever,$H27))) -> 0.225 | J27: =IF($D27="Pass-through",$G27,IF($I27>=1,$G27,ROUND($G27/(1-$I27),0))) -> 516 | K27: =$F27*$J27 -> 2580 | L27: =$F27*$G27 -> 2000 | M27: =$F27*N('Rate Card'!E27) -> 2.5 | N27: =$F27*N('Rate Card'!G27) -> 0
B28: ='Rate Card'!A28 -> SSU | C28: ='Rate Card'!B28 -> Pre-feasibility form development | D28: ='Rate Card'!C28 -> Service | E28: ='Rate Card'!D28 -> Fixed | F28: =IF($A28="x",IFERROR(INDEX(DriverQty,MATCH($E28,DriverName,0)),0),0) -> 0 | G28: ='Rate Card'!I28 -> 3200 | I28: =IF($D28="Pass-through",0,MAX(MarginFloor,IF($H28="",MarginLever,$H28))) -> 0.225 | J28: =IF($D28="Pass-through",$G28,IF($I28>=1,$G28,ROUND($G28/(1-$I28),0))) -> 4129 | K28: =$F28*$J28 -> 0 | L28: =$F28*$G28 -> 0 | M28: =$F28*N('Rate Card'!E28) -> 0 | N28: =$F28*N('Rate Card'!G28) -> 0
A29: x | B29: ='Rate Card'!A29 -> SSU | C29: ='Rate Card'!B29 -> Pre-feasibility | D29: ='Rate Card'!C29 -> Service | E29: ='Rate Card'!D29 -> Per site | F29: =IF($A29="x",IFERROR(INDEX(DriverQty,MATCH($E29,DriverName,0)),0),0) -> 5 | G29: ='Rate Card'!I29 -> 1200 | I29: =IF($D29="Pass-through",0,MAX(MarginFloor,IF($H29="",MarginLever,$H29))) -> 0.225 | J29: =IF($D29="Pass-through",$G29,IF($I29>=1,$G29,ROUND($G29/(1-$I29),0))) -> 1548 | K29: =$F29*$J29 -> 7740 | L29: =$F29*$G29 -> 6000 | M29: =$F29*N('Rate Card'!E29) -> 7.5 | N29: =$F29*N('Rate Card'!G29) -> 0
A30: x | B30: ='Rate Card'!A30 -> SSU | C30: ='Rate Card'!B30 -> Feasibility | D30: ='Rate Card'!C30 -> Service | E30: ='Rate Card'!D30 -> Per site | F30: =IF($A30="x",IFERROR(INDEX(DriverQty,MATCH($E30,DriverName,0)),0),0) -> 5 | G30: ='Rate Card'!I30 -> 4200 | I30: =IF($D30="Pass-through",0,MAX(MarginFloor,IF($H30="",MarginLever,$H30))) -> 0.225 | J30: =IF($D30="Pass-through",$G30,IF($I30>=1,$G30,ROUND($G30/(1-$I30),0))) -> 5419 | K30: =$F30*$J30 -> 27095 | L30: =$F30*$G30 -> 21000 | M30: =$F30*N('Rate Card'!E30) -> 7.5 | N30: =$F30*N('Rate Card'!G30) -> 5
B31: ='Rate Card'!A31 -> SSU | C31: ='Rate Card'!B31 -> Feasibility Report | D31: ='Rate Card'!C31 -> Service | E31: ='Rate Card'!D31 -> Fixed | F31: =IF($A31="x",IFERROR(INDEX(DriverQty,MATCH($E31,DriverName,0)),0),0) -> 0 | G31: ='Rate Card'!I31 -> 3200 | I31: =IF($D31="Pass-through",0,MAX(MarginFloor,IF($H31="",MarginLever,$H31))) -> 0.225 | J31: =IF($D31="Pass-through",$G31,IF($I31>=1,$G31,ROUND($G31/(1-$I31),0))) -> 4129 | K31: =$F31*$J31 -> 0 | L31: =$F31*$G31 -> 0 | M31: =$F31*N('Rate Card'!E31) -> 0 | N31: =$F31*N('Rate Card'!G31) -> 0
A32: x | B32: ='Rate Card'!A32 -> SSU | C32: ='Rate Card'!B32 -> Essential document collection | D32: ='Rate Card'!C32 -> Service | E32: ='Rate Card'!D32 -> Per site | F32: =IF($A32="x",IFERROR(INDEX(DriverQty,MATCH($E32,DriverName,0)),0),0) -> 5 | G32: ='Rate Card'!I32 -> 1600 | I32: =IF($D32="Pass-through",0,MAX(MarginFloor,IF($H32="",MarginLever,$H32))) -> 0.225 | J32: =IF($D32="Pass-through",$G32,IF($I32>=1,$G32,ROUND($G32/(1-$I32),0))) -> 2065 | K32: =$F32*$J32 -> 10325 | L32: =$F32*$G32 -> 8000 | M32: =$F32*N('Rate Card'!E32) -> 10 | N32: =$F32*N('Rate Card'!G32) -> 0
B33: ='Rate Card'!A33 -> SSU | C33: ='Rate Card'!B33 -> PSQV - preparation | D33: ='Rate Card'!C33 -> Service | E33: ='Rate Card'!D33 -> Per site | F33: =IF($A33="x",IFERROR(INDEX(DriverQty,MATCH($E33,DriverName,0)),0),0) -> 0 | G33: ='Rate Card'!I33 -> 3200 | I33: =IF($D33="Pass-through",0,MAX(MarginFloor,IF($H33="",MarginLever,$H33))) -> 0.225 | J33: =IF($D33="Pass-through",$G33,IF($I33>=1,$G33,ROUND($G33/(1-$I33),0))) -> 4129 | K33: =$F33*$J33 -> 0 | L33: =$F33*$G33 -> 0 | M33: =$F33*N('Rate Card'!E33) -> 0 | N33: =$F33*N('Rate Card'!G33) -> 0
B34: ='Rate Card'!A34 -> SSU | C34: ='Rate Card'!B34 -> PSQV - visit & report | D34: ='Rate Card'!C34 -> Service | E34: ='Rate Card'!D34 -> Per site | F34: =IF($A34="x",IFERROR(INDEX(DriverQty,MATCH($E34,DriverName,0)),0),0) -> 0 | G34: ='Rate Card'!I34 -> 6400 | I34: =IF($D34="Pass-through",0,MAX(MarginFloor,IF($H34="",MarginLever,$H34))) -> 0.225 | J34: =IF($D34="Pass-through",$G34,IF($I34>=1,$G34,ROUND($G34/(1-$I34),0))) -> 8258 | K34: =$F34*$J34 -> 0 | L34: =$F34*$G34 -> 0 | M34: =$F34*N('Rate Card'!E34) -> 0 | N34: =$F34*N('Rate Card'!G34) -> 0
B35: ='Rate Card'!A35 -> SSU | C35: ='Rate Card'!B35 -> PSQV - local travel | D35: ='Rate Card'!C35 -> Service | E35: ='Rate Card'!D35 -> Per site | F35: =IF($A35="x",IFERROR(INDEX(DriverQty,MATCH($E35,DriverName,0)),0),0) -> 0 | G35: ='Rate Card'!I35 -> 4000 | I35: =IF($D35="Pass-through",0,MAX(MarginFloor,IF($H35="",MarginLever,$H35))) -> 0.225 | J35: =IF($D35="Pass-through",$G35,IF($I35>=1,$G35,ROUND($G35/(1-$I35),0))) -> 5161 | K35: =$F35*$J35 -> 0 | L35: =$F35*$G35 -> 0 | M35: =$F35*N('Rate Card'!E35) -> 0 | N35: =$F35*N('Rate Card'!G35) -> 0
B36: ='Rate Card'!A36 -> SSU | C36: ='Rate Card'!B36 -> PSQV - Out-station travel | D36: ='Rate Card'!C36 -> Service | E36: ='Rate Card'!D36 -> Per site | F36: =IF($A36="x",IFERROR(INDEX(DriverQty,MATCH($E36,DriverName,0)),0),0) -> 0 | G36: ='Rate Card'!I36 -> 8000 | I36: =IF($D36="Pass-through",0,MAX(MarginFloor,IF($H36="",MarginLever,$H36))) -> 0.225 | J36: =IF($D36="Pass-through",$G36,IF($I36>=1,$G36,ROUND($G36/(1-$I36),0))) -> 10323 | K36: =$F36*$J36 -> 0 | L36: =$F36*$G36 -> 0 | M36: =$F36*N('Rate Card'!E36) -> 0 | N36: =$F36*N('Rate Card'!G36) -> 0
A37: x | B37: ='Rate Card'!A37 -> SSU | C37: ='Rate Card'!B37 -> CSA/MoU development | D37: ='Rate Card'!C37 -> Service | E37: ='Rate Card'!D37 -> Fixed | F37: =IF($A37="x",IFERROR(INDEX(DriverQty,MATCH($E37,DriverName,0)),0),0) -> 1 | G37: ='Rate Card'!I37 -> 8300 | I37: =IF($D37="Pass-through",0,MAX(MarginFloor,IF($H37="",MarginLever,$H37))) -> 0.225 | J37: =IF($D37="Pass-through",$G37,IF($I37>=1,$G37,ROUND($G37/(1-$I37),0))) -> 10710 | K37: =$F37*$J37 -> 10710 | L37: =$F37*$G37 -> 8300 | M37: =$F37*N('Rate Card'!E37) -> 8.5 | N37: =$F37*N('Rate Card'!G37) -> 0.5
A38: x | B38: ='Rate Card'!A38 -> SSU | C38: ='Rate Card'!B38 -> CSA/MoU negotiation | D38: ='Rate Card'!C38 -> Service | E38: ='Rate Card'!D38 -> Per site | F38: =IF($A38="x",IFERROR(INDEX(DriverQty,MATCH($E38,DriverName,0)),0),0) -> 5 | G38: ='Rate Card'!I38 -> 1600 | I38: =IF($D38="Pass-through",0,MAX(MarginFloor,IF($H38="",MarginLever,$H38))) -> 0.225 | J38: =IF($D38="Pass-through",$G38,IF($I38>=1,$G38,ROUND($G38/(1-$I38),0))) -> 2065 | K38: =$F38*$J38 -> 10325 | L38: =$F38*$G38 -> 8000 | M38: =$F38*N('Rate Card'!E38) -> 10 | N38: =$F38*N('Rate Card'!G38) -> 0
A39: x | B39: ='Rate Card'!A39 -> SSU | C39: ='Rate Card'!B39 -> EC Dossier preparation | D39: ='Rate Card'!C39 -> Service | E39: ='Rate Card'!D39 -> Per site | F39: =IF($A39="x",IFERROR(INDEX(DriverQty,MATCH($E39,DriverName,0)),0),0) -> 5 | G39: ='Rate Card'!I39 -> 3200 | I39: =IF($D39="Pass-through",0,MAX(MarginFloor,IF($H39="",MarginLever,$H39))) -> 0.225 | J39: =IF($D39="Pass-through",$G39,IF($I39>=1,$G39,ROUND($G39/(1-$I39),0))) -> 4129 | K39: =$F39*$J39 -> 20645 | L39: =$F39*$G39 -> 16000 | M39: =$F39*N('Rate Card'!E39) -> 20 | N39: =$F39*N('Rate Card'!G39) -> 0
A40: x | B40: ='Rate Card'!A40 -> SSU | C40: ='Rate Card'!B40 -> EC Dossier online submission | D40: ='Rate Card'!C40 -> Service | E40: ='Rate Card'!D40 -> Per site | F40: =IF($A40="x",IFERROR(INDEX(DriverQty,MATCH($E40,DriverName,0)),0),0) -> 5 | G40: ='Rate Card'!I40 -> 1600 | I40: =IF($D40="Pass-through",0,MAX(MarginFloor,IF($H40="",MarginLever,$H40))) -> 0.225 | J40: =IF($D40="Pass-through",$G40,IF($I40>=1,$G40,ROUND($G40/(1-$I40),0))) -> 2065 | K40: =$F40*$J40 -> 10325 | L40: =$F40*$G40 -> 8000 | M40: =$F40*N('Rate Card'!E40) -> 10 | N40: =$F40*N('Rate Card'!G40) -> 0
B41: ='Rate Card'!A41 -> SSU | C41: ='Rate Card'!B41 -> EC Dossier offline submission | D41: ='Rate Card'!C41 -> Service | E41: ='Rate Card'!D41 -> Per site | F41: =IF($A41="x",IFERROR(INDEX(DriverQty,MATCH($E41,DriverName,0)),0),0) -> 0 | G41: ='Rate Card'!I41 -> 6400 | I41: =IF($D41="Pass-through",0,MAX(MarginFloor,IF($H41="",MarginLever,$H41))) -> 0.225 | J41: =IF($D41="Pass-through",$G41,IF($I41>=1,$G41,ROUND($G41/(1-$I41),0))) -> 8258 | K41: =$F41*$J41 -> 0 | L41: =$F41*$G41 -> 0 | M41: =$F41*N('Rate Card'!E41) -> 0 | N41: =$F41*N('Rate Card'!G41) -> 0
B42: ='Rate Card'!A42 -> SSU | C42: ='Rate Card'!B42 -> EC Communication | D42: ='Rate Card'!C42 -> Service | E42: ='Rate Card'!D42 -> Per site | F42: =IF($A42="x",IFERROR(INDEX(DriverQty,MATCH($E42,DriverName,0)),0),0) -> 0 | G42: ='Rate Card'!I42 -> 3200 | I42: =IF($D42="Pass-through",0,MAX(MarginFloor,IF($H42="",MarginLever,$H42))) -> 0.225 | J42: =IF($D42="Pass-through",$G42,IF($I42>=1,$G42,ROUND($G42/(1-$I42),0))) -> 4129 | K42: =$F42*$J42 -> 0 | L42: =$F42*$G42 -> 0 | M42: =$F42*N('Rate Card'!E42) -> 0 | N42: =$F42*N('Rate Card'!G42) -> 0
A43: x | B43: ='Rate Card'!A43 -> SSU | C43: ='Rate Card'!B43 -> Finance & Admin - A/C setup | D43: ='Rate Card'!C43 -> Service | E43: ='Rate Card'!D43 -> Per site | F43: =IF($A43="x",IFERROR(INDEX(DriverQty,MATCH($E43,DriverName,0)),0),0) -> 5 | G43: ='Rate Card'!I43 -> 1600 | I43: =IF($D43="Pass-through",0,MAX(MarginFloor,IF($H43="",MarginLever,$H43))) -> 0.225 | J43: =IF($D43="Pass-through",$G43,IF($I43>=1,$G43,ROUND($G43/(1-$I43),0))) -> 2065 | K43: =$F43*$J43 -> 10325 | L43: =$F43*$G43 -> 8000 | M43: =$F43*N('Rate Card'!E43) -> 10 | N43: =$F43*N('Rate Card'!G43) -> 0
B44: ='Rate Card'!A44 -> SSU | C44: ='Rate Card'!B44 -> SIV Dossier Printing & Dispatch | D44: ='Rate Card'!C44 -> Service | E44: ='Rate Card'!D44 -> Per site | F44: =IF($A44="x",IFERROR(INDEX(DriverQty,MATCH($E44,DriverName,0)),0),0) -> 0 | G44: ='Rate Card'!I44 -> 6400 | I44: =IF($D44="Pass-through",0,MAX(MarginFloor,IF($H44="",MarginLever,$H44))) -> 0.225 | J44: =IF($D44="Pass-through",$G44,IF($I44>=1,$G44,ROUND($G44/(1-$I44),0))) -> 8258 | K44: =$F44*$J44 -> 0 | L44: =$F44*$G44 -> 0 | M44: =$F44*N('Rate Card'!E44) -> 0 | N44: =$F44*N('Rate Card'!G44) -> 0
B45: ='Rate Card'!A45 -> SSU | C45: ='Rate Card'!B45 -> Site Handover | D45: ='Rate Card'!C45 -> Service | E45: ='Rate Card'!D45 -> Per site | F45: =IF($A45="x",IFERROR(INDEX(DriverQty,MATCH($E45,DriverName,0)),0),0) -> 0 | G45: ='Rate Card'!I45 -> 3200 | I45: =IF($D45="Pass-through",0,MAX(MarginFloor,IF($H45="",MarginLever,$H45))) -> 0.225 | J45: =IF($D45="Pass-through",$G45,IF($I45>=1,$G45,ROUND($G45/(1-$I45),0))) -> 4129 | K45: =$F45*$J45 -> 0 | L45: =$F45*$G45 -> 0 | M45: =$F45*N('Rate Card'!E45) -> 0 | N45: =$F45*N('Rate Card'!G45) -> 0
A46: x | B46: ='Rate Card'!A46 -> SSU | C46: ='Rate Card'!B46 -> TMF Support | D46: ='Rate Card'!C46 -> Service | E46: ='Rate Card'!D46 -> Per site | F46: =IF($A46="x",IFERROR(INDEX(DriverQty,MATCH($E46,DriverName,0)),0),0) -> 5 | G46: ='Rate Card'!I46 -> 9600 | I46: =IF($D46="Pass-through",0,MAX(MarginFloor,IF($H46="",MarginLever,$H46))) -> 0.225 | J46: =IF($D46="Pass-through",$G46,IF($I46>=1,$G46,ROUND($G46/(1-$I46),0))) -> 12387 | K46: =$F46*$J46 -> 61935 | L46: =$F46*$G46 -> 48000 | M46: =$F46*N('Rate Card'!E46) -> 60 | N46: =$F46*N('Rate Card'!G46) -> 0
B47: ='Rate Card'!A47 -> SSU | C47: ='Rate Card'!B47 -> ISF Support | D47: ='Rate Card'!C47 -> Service | E47: ='Rate Card'!D47 -> Per site | F47: =IF($A47="x",IFERROR(INDEX(DriverQty,MATCH($E47,DriverName,0)),0),0) -> 0 | G47: ='Rate Card'!I47 -> 12800 | I47: =IF($D47="Pass-through",0,MAX(MarginFloor,IF($H47="",MarginLever,$H47))) -> 0.225 | J47: =IF($D47="Pass-through",$G47,IF($I47>=1,$G47,ROUND($G47/(1-$I47),0))) -> 16516 | K47: =$F47*$J47 -> 0 | L47: =$F47*$G47 -> 0 | M47: =$F47*N('Rate Card'!E47) -> 0 | N47: =$F47*N('Rate Card'!G47) -> 0
B48: ='Rate Card'!A48 -> SSU | C48: ='Rate Card'!B48 -> eISF support | D48: ='Rate Card'!C48 -> Service | E48: ='Rate Card'!D48 -> Per site | F48: =IF($A48="x",IFERROR(INDEX(DriverQty,MATCH($E48,DriverName,0)),0),0) -> 0 | G48: ='Rate Card'!I48 -> 0 | I48: =IF($D48="Pass-through",0,MAX(MarginFloor,IF($H48="",MarginLever,$H48))) -> 0.225 | J48: =IF($D48="Pass-through",$G48,IF($I48>=1,$G48,ROUND($G48/(1-$I48),0))) -> 0 | K48: =$F48*$J48 -> 0 | L48: =$F48*$G48 -> 0 | M48: =$F48*N('Rate Card'!E48) -> 0 | N48: =$F48*N('Rate Card'!G48) -> 0
B49: ='Rate Card'!A49 -> DM | C49: ='Rate Card'!B49 -> Protocol Training | D49: ='Rate Card'!C49 -> Service | E49: ='Rate Card'!D49 -> Fixed | F49: =IF($A49="x",IFERROR(INDEX(DriverQty,MATCH($E49,DriverName,0)),0),0) -> 0 | G49: ='Rate Card'!I49 -> 21250 | I49: =IF($D49="Pass-through",0,MAX(MarginFloor,IF($H49="",MarginLever,$H49))) -> 0.225 | J49: =IF($D49="Pass-through",$G49,IF($I49>=1,$G49,ROUND($G49/(1-$I49),0))) -> 27419 | K49: =$F49*$J49 -> 0 | L49: =$F49*$G49 -> 0 | M49: =$F49*N('Rate Card'!E49) -> 0 | N49: =$F49*N('Rate Card'!G49) -> 0
A50: x | B50: ='Rate Card'!A50 -> DM | C50: ='Rate Card'!B50 -> DMP development and finalization | D50: ='Rate Card'!C50 -> Service | E50: ='Rate Card'!D50 -> Fixed | F50: =IF($A50="x",IFERROR(INDEX(DriverQty,MATCH($E50,DriverName,0)),0),0) -> 1 | G50: ='Rate Card'!I50 -> 48500 | I50: =IF($D50="Pass-through",0,MAX(MarginFloor,IF($H50="",MarginLever,$H50))) -> 0.225 | J50: =IF($D50="Pass-through",$G50,IF($I50>=1,$G50,ROUND($G50/(1-$I50),0))) -> 62581 | K50: =$F50*$J50 -> 62581 | L50: =$F50*$G50 -> 48500 | M50: =$F50*N('Rate Card'!E50) -> 50 | N50: =$F50*N('Rate Card'!G50) -> 2
A51: x | B51: ='Rate Card'!A51 -> DM | C51: ='Rate Card'!B51 -> CRF Development (upto 50 pages) | D51: ='Rate Card'!C51 -> Service | E51: ='Rate Card'!D51 -> Fixed | F51: =IF($A51="x",IFERROR(INDEX(DriverQty,MATCH($E51,DriverName,0)),0),0) -> 1 | G51: ='Rate Card'!I51 -> 102000 | I51: =IF($D51="Pass-through",0,MAX(MarginFloor,IF($H51="",MarginLever,$H51))) -> 0.225 | J51: =IF($D51="Pass-through",$G51,IF($I51>=1,$G51,ROUND($G51/(1-$I51),0))) -> 131613 | K51: =$F51*$J51 -> 131613 | L51: =$F51*$G51 -> 102000 | M51: =$F51*N('Rate Card'!E51) -> 120 | N51: =$F51*N('Rate Card'!G51) -> 0
A52: x | B52: ='Rate Card'!A52 -> DM | C52: ='Rate Card'!B52 -> CRF Finalization | D52: ='Rate Card'!C52 -> Service | E52: ='Rate Card'!D52 -> Fixed | F52: =IF($A52="x",IFERROR(INDEX(DriverQty,MATCH($E52,DriverName,0)),0),0) -> 1 | G52: ='Rate Card'!I52 -> 45500 | I52: =IF($D52="Pass-through",0,MAX(MarginFloor,IF($H52="",MarginLever,$H52))) -> 0.225 | J52: =IF($D52="Pass-through",$G52,IF($I52>=1,$G52,ROUND($G52/(1-$I52),0))) -> 58710 | K52: =$F52*$J52 -> 58710 | L52: =$F52*$G52 -> 45500 | M52: =$F52*N('Rate Card'!E52) -> 50 | N52: =$F52*N('Rate Card'!G52) -> 1
B53: ='Rate Card'!A53 -> DM | C53: ='Rate Card'!B53 -> DCF development (on paper CRF) | D53: ='Rate Card'!C53 -> Service | E53: ='Rate Card'!D53 -> Fixed | F53: =IF($A53="x",IFERROR(INDEX(DriverQty,MATCH($E53,DriverName,0)),0),0) -> 0 | G53: ='Rate Card'!I53 -> 34000 | I53: =IF($D53="Pass-through",0,MAX(MarginFloor,IF($H53="",MarginLever,$H53))) -> 0.225 | J53: =IF($D53="Pass-through",$G53,IF($I53>=1,$G53,ROUND($G53/(1-$I53),0))) -> 43871 | K53: =$F53*$J53 -> 0 | L53: =$F53*$G53 -> 0 | M53: =$F53*N('Rate Card'!E53) -> 0 | N53: =$F53*N('Rate Card'!G53) -> 0
B54: ='Rate Card'!A54 -> DM | C54: ='Rate Card'!B54 -> DCF development (no paper CRF) | D54: ='Rate Card'!C54 -> Service | E54: ='Rate Card'!D54 -> Fixed | F54: =IF($A54="x",IFERROR(INDEX(DriverQty,MATCH($E54,DriverName,0)),0),0) -> 0 | G54: ='Rate Card'!I54 -> 68000 | I54: =IF($D54="Pass-through",0,MAX(MarginFloor,IF($H54="",MarginLever,$H54))) -> 0.225 | J54: =IF($D54="Pass-through",$G54,IF($I54>=1,$G54,ROUND($G54/(1-$I54),0))) -> 87742 | K54: =$F54*$J54 -> 0 | L54: =$F54*$G54 -> 0 | M54: =$F54*N('Rate Card'!E54) -> 0 | N54: =$F54*N('Rate Card'!G54) -> 0
A55: x | B55: ='Rate Card'!A55 -> DM | C55: ='Rate Card'!B55 -> EDC finalization | D55: ='Rate Card'!C55 -> Service | E55: ='Rate Card'!D55 -> Fixed | F55: =IF($A55="x",IFERROR(INDEX(DriverQty,MATCH($E55,DriverName,0)),0),0) -> 1 | G55: ='Rate Card'!I55 -> 42500 | I55: =IF($D55="Pass-through",0,MAX(MarginFloor,IF($H55="",MarginLever,$H55))) -> 0.225 | J55: =IF($D55="Pass-through",$G55,IF($I55>=1,$G55,ROUND($G55/(1-$I55),0))) -> 54839 | K55: =$F55*$J55 -> 54839 | L55: =$F55*$G55 -> 42500 | M55: =$F55*N('Rate Card'!E55) -> 50 | N55: =$F55*N('Rate Card'!G55) -> 0
B56: ='Rate Card'!A56 -> DM | C56: ='Rate Card'!B56 -> EDC UAT- Demo | D56: ='Rate Card'!C56 -> Service | E56: ='Rate Card'!D56 -> Fixed | F56: =IF($A56="x",IFERROR(INDEX(DriverQty,MATCH($E56,DriverName,0)),0),0) -> 0 | G56: ='Rate Card'!I56 -> 68000 | I56: =IF($D56="Pass-through",0,MAX(MarginFloor,IF($H56="",MarginLever,$H56))) -> 0.225 | J56: =IF($D56="Pass-through",$G56,IF($I56>=1,$G56,ROUND($G56/(1-$I56),0))) -> 87742 | K56: =$F56*$J56 -> 0 | L56: =$F56*$G56 -> 0 | M56: =$F56*N('Rate Card'!E56) -> 0 | N56: =$F56*N('Rate Card'!G56) -> 0
B57: ='Rate Card'!A57 -> DM | C57: ='Rate Card'!B57 -> EDC UAT- Production | D57: ='Rate Card'!C57 -> Service | E57: ='Rate Card'!D57 -> Fixed | F57: =IF($A57="x",IFERROR(INDEX(DriverQty,MATCH($E57,DriverName,0)),0),0) -> 0 | G57: ='Rate Card'!I57 -> 7250 | I57: =IF($D57="Pass-through",0,MAX(MarginFloor,IF($H57="",MarginLever,$H57))) -> 0.225 | J57: =IF($D57="Pass-through",$G57,IF($I57>=1,$G57,ROUND($G57/(1-$I57),0))) -> 9355 | K57: =$F57*$J57 -> 0 | L57: =$F57*$G57 -> 0 | M57: =$F57*N('Rate Card'!E57) -> 0 | N57: =$F57*N('Rate Card'!G57) -> 0
B58: ='Rate Card'!A58 -> DM | C58: ='Rate Card'!B58 -> Data Digitization | D58: ='Rate Card'!C58 -> Service | E58: ='Rate Card'!D58 -> Per visit | F58: =IF($A58="x",IFERROR(INDEX(DriverQty,MATCH($E58,DriverName,0)),0),0) -> 0 | G58: ='Rate Card'!I58 -> 850 | I58: =IF($D58="Pass-through",0,MAX(MarginFloor,IF($H58="",MarginLever,$H58))) -> 0.225 | J58: =IF($D58="Pass-through",$G58,IF($I58>=1,$G58,ROUND($G58/(1-$I58),0))) -> 1097 | K58: =$F58*$J58 -> 0 | L58: =$F58*$G58 -> 0 | M58: =$F58*N('Rate Card'!E58) -> 0 | N58: =$F58*N('Rate Card'!G58) -> 0
B59: ='Rate Card'!A59 -> DM | C59: ='Rate Card'!B59 -> Trackers update | D59: ='Rate Card'!C59 -> Service | E59: ='Rate Card'!D59 -> Per month | F59: =IF($A59="x",IFERROR(INDEX(DriverQty,MATCH($E59,DriverName,0)),0),0) -> 0 | G59: ='Rate Card'!I59 -> 31275 | I59: =IF($D59="Pass-through",0,MAX(MarginFloor,IF($H59="",MarginLever,$H59))) -> 0.225 | J59: =IF($D59="Pass-through",$G59,IF($I59>=1,$G59,ROUND($G59/(1-$I59),0))) -> 40355 | K59: =$F59*$J59 -> 0 | L59: =$F59*$G59 -> 0 | M59: =$F59*N('Rate Card'!E59) -> 0 | N59: =$F59*N('Rate Card'!G59) -> 0
B60: ='Rate Card'!A60 -> DM | C60: ='Rate Card'!B60 -> EDC completion guidelines | D60: ='Rate Card'!C60 -> Service | E60: ='Rate Card'!D60 -> Fixed | F60: =IF($A60="x",IFERROR(INDEX(DriverQty,MATCH($E60,DriverName,0)),0),0) -> 0 | G60: ='Rate Card'!I60 -> 54000 | I60: =IF($D60="Pass-through",0,MAX(MarginFloor,IF($H60="",MarginLever,$H60))) -> 0.225 | J60: =IF($D60="Pass-through",$G60,IF($I60>=1,$G60,ROUND($G60/(1-$I60),0))) -> 69677 | K60: =$F60*$J60 -> 0 | L60: =$F60*$G60 -> 0 | M60: =$F60*N('Rate Card'!E60) -> 0 | N60: =$F60*N('Rate Card'!G60) -> 0
B61: ='Rate Card'!A61 -> DM | C61: ='Rate Card'!B61 -> Patient Diary (if required) | D61: ='Rate Card'!C61 -> Service | E61: ='Rate Card'!D61 -> Fixed | F61: =IF($A61="x",IFERROR(INDEX(DriverQty,MATCH($E61,DriverName,0)),0),0) -> 0 | G61: ='Rate Card'!I61 -> 25500 | I61: =IF($D61="Pass-through",0,MAX(MarginFloor,IF($H61="",MarginLever,$H61))) -> 0.225 | J61: =IF($D61="Pass-through",$G61,IF($I61>=1,$G61,ROUND($G61/(1-$I61),0))) -> 32903 | K61: =$F61*$J61 -> 0 | L61: =$F61*$G61 -> 0 | M61: =$F61*N('Rate Card'!E61) -> 0 | N61: =$F61*N('Rate Card'!G61) -> 0
B62: ='Rate Card'!A62 -> DM | C62: ='Rate Card'!B62 -> Patient dairy completion guidelines | D62: ='Rate Card'!C62 -> Service | E62: ='Rate Card'!D62 -> Fixed | F62: =IF($A62="x",IFERROR(INDEX(DriverQty,MATCH($E62,DriverName,0)),0),0) -> 0 | G62: ='Rate Card'!I62 -> 17000 | I62: =IF($D62="Pass-through",0,MAX(MarginFloor,IF($H62="",MarginLever,$H62))) -> 0.225 | J62: =IF($D62="Pass-through",$G62,IF($I62>=1,$G62,ROUND($G62/(1-$I62),0))) -> 21935 | K62: =$F62*$J62 -> 0 | L62: =$F62*$G62 -> 0 | M62: =$F62*N('Rate Card'!E62) -> 0 | N62: =$F62*N('Rate Card'!G62) -> 0
B63: ='Rate Card'!A63 -> DM | C63: ='Rate Card'!B63 -> Data QC (per visit) [Prospective] | D63: ='Rate Card'!C63 -> Service | E63: ='Rate Card'!D63 -> Per visit | F63: =IF($A63="x",IFERROR(INDEX(DriverQty,MATCH($E63,DriverName,0)),0),0) -> 0 | G63: ='Rate Card'!I63 -> 1700 | I63: =IF($D63="Pass-through",0,MAX(MarginFloor,IF($H63="",MarginLever,$H63))) -> 0.225 | J63: =IF($D63="Pass-through",$G63,IF($I63>=1,$G63,ROUND($G63/(1-$I63),0))) -> 2194 | K63: =$F63*$J63 -> 0 | L63: =$F63*$G63 -> 0 | M63: =$F63*N('Rate Card'!E63) -> 0 | N63: =$F63*N('Rate Card'!G63) -> 0
B64: ='Rate Card'!A64 -> DM | C64: ='Rate Card'!B64 -> Query generation (per visit) [Prospective] | D64: ='Rate Card'!C64 -> Service | E64: ='Rate Card'!D64 -> Per visit | F64: =IF($A64="x",IFERROR(INDEX(DriverQty,MATCH($E64,DriverName,0)),0),0) -> 0 | G64: ='Rate Card'!I64 -> 425 | I64: =IF($D64="Pass-through",0,MAX(MarginFloor,IF($H64="",MarginLever,$H64))) -> 0.225 | J64: =IF($D64="Pass-through",$G64,IF($I64>=1,$G64,ROUND($G64/(1-$I64),0))) -> 548 | K64: =$F64*$J64 -> 0 | L64: =$F64*$G64 -> 0 | M64: =$F64*N('Rate Card'!E64) -> 0 | N64: =$F64*N('Rate Card'!G64) -> 0
B65: ='Rate Card'!A65 -> DM | C65: ='Rate Card'!B65 -> Query resolution (per visit) [Prospective] | D65: ='Rate Card'!C65 -> Service | E65: ='Rate Card'!D65 -> Per visit | F65: =IF($A65="x",IFERROR(INDEX(DriverQty,MATCH($E65,DriverName,0)),0),0) -> 0 | G65: ='Rate Card'!I65 -> 425 | I65: =IF($D65="Pass-through",0,MAX(MarginFloor,IF($H65="",MarginLever,$H65))) -> 0.225 | J65: =IF($D65="Pass-through",$G65,IF($I65>=1,$G65,ROUND($G65/(1-$I65),0))) -> 548 | K65: =$F65*$J65 -> 0 | L65: =$F65*$G65 -> 0 | M65: =$F65*N('Rate Card'!E65) -> 0 | N65: =$F65*N('Rate Card'!G65) -> 0
B66: ='Rate Card'!A66 -> DM | C66: ='Rate Card'!B66 -> Final data harmonization [Prospective] | D66: ='Rate Card'!C66 -> Service | E66: ='Rate Card'!D66 -> Fixed | F66: =IF($A66="x",IFERROR(INDEX(DriverQty,MATCH($E66,DriverName,0)),0),0) -> 0 | G66: ='Rate Card'!I66 -> 5525 | I66: =IF($D66="Pass-through",0,MAX(MarginFloor,IF($H66="",MarginLever,$H66))) -> 0.225 | J66: =IF($D66="Pass-through",$G66,IF($I66>=1,$G66,ROUND($G66/(1-$I66),0))) -> 7129 | K66: =$F66*$J66 -> 0 | L66: =$F66*$G66 -> 0 | M66: =$F66*N('Rate Card'!E66) -> 0 | N66: =$F66*N('Rate Card'!G66) -> 0
A67: x | B67: ='Rate Card'!A67 -> DM | C67: ='Rate Card'!B67 -> Data QC (per visit) [Retrospective] | D67: ='Rate Card'!C67 -> Service | E67: ='Rate Card'!D67 -> Per visit | F67: =IF($A67="x",IFERROR(INDEX(DriverQty,MATCH($E67,DriverName,0)),0),0) -> 750 | G67: ='Rate Card'!I67 -> 1700 | I67: =IF($D67="Pass-through",0,MAX(MarginFloor,IF($H67="",MarginLever,$H67))) -> 0.225 | J67: =IF($D67="Pass-through",$G67,IF($I67>=1,$G67,ROUND($G67/(1-$I67),0))) -> 2194 | K67: =$F67*$J67 -> 1645500 | L67: =$F67*$G67 -> 1275000 | M67: =$F67*N('Rate Card'!E67) -> 1500 | N67: =$F67*N('Rate Card'!G67) -> 0
A68: x | B68: ='Rate Card'!A68 -> DM | C68: ='Rate Card'!B68 -> Query generation (per visit) [Retrospective] | D68: ='Rate Card'!C68 -> Service | E68: ='Rate Card'!D68 -> Per visit | F68: =IF($A68="x",IFERROR(INDEX(DriverQty,MATCH($E68,DriverName,0)),0),0) -> 750 | G68: ='Rate Card'!I68 -> 850 | I68: =IF($D68="Pass-through",0,MAX(MarginFloor,IF($H68="",MarginLever,$H68))) -> 0.225 | J68: =IF($D68="Pass-through",$G68,IF($I68>=1,$G68,ROUND($G68/(1-$I68),0))) -> 1097 | K68: =$F68*$J68 -> 822750 | L68: =$F68*$G68 -> 637500 | M68: =$F68*N('Rate Card'!E68) -> 750 | N68: =$F68*N('Rate Card'!G68) -> 0
A69: x | B69: ='Rate Card'!A69 -> DM | C69: ='Rate Card'!B69 -> Query resolution (per visit) [Retrospective] | D69: ='Rate Card'!C69 -> Service | E69: ='Rate Card'!D69 -> Per visit | F69: =IF($A69="x",IFERROR(INDEX(DriverQty,MATCH($E69,DriverName,0)),0),0) -> 750 | G69: ='Rate Card'!I69 -> 850 | I69: =IF($D69="Pass-through",0,MAX(MarginFloor,IF($H69="",MarginLever,$H69))) -> 0.225 | J69: =IF($D69="Pass-through",$G69,IF($I69>=1,$G69,ROUND($G69/(1-$I69),0))) -> 1097 | K69: =$F69*$J69 -> 822750 | L69: =$F69*$G69 -> 637500 | M69: =$F69*N('Rate Card'!E69) -> 750 | N69: =$F69*N('Rate Card'!G69) -> 0
A70: x | B70: ='Rate Card'!A70 -> DM | C70: ='Rate Card'!B70 -> Final data harmonization [Retrospective] | D70: ='Rate Card'!C70 -> Service | E70: ='Rate Card'!D70 -> Fixed | F70: =IF($A70="x",IFERROR(INDEX(DriverQty,MATCH($E70,DriverName,0)),0),0) -> 1 | G70: ='Rate Card'!I70 -> 5525 | I70: =IF($D70="Pass-through",0,MAX(MarginFloor,IF($H70="",MarginLever,$H70))) -> 0.225 | J70: =IF($D70="Pass-through",$G70,IF($I70>=1,$G70,ROUND($G70/(1-$I70),0))) -> 7129 | K70: =$F70*$J70 -> 7129 | L70: =$F70*$G70 -> 5525 | M70: =$F70*N('Rate Card'!E70) -> 6.5 | N70: =$F70*N('Rate Card'!G70) -> 0
B71: ='Rate Card'!A71 -> PM | C71: ='Rate Card'!B71 -> Protocol Training | D71: ='Rate Card'!C71 -> Service | E71: ='Rate Card'!D71 -> Fixed | F71: =IF($A71="x",IFERROR(INDEX(DriverQty,MATCH($E71,DriverName,0)),0),0) -> 0 | G71: ='Rate Card'!I71 -> 8400 | I71: =IF($D71="Pass-through",0,MAX(MarginFloor,IF($H71="",MarginLever,$H71))) -> 0.225 | J71: =IF($D71="Pass-through",$G71,IF($I71>=1,$G71,ROUND($G71/(1-$I71),0))) -> 10839 | K71: =$F71*$J71 -> 0 | L71: =$F71*$G71 -> 0 | M71: =$F71*N('Rate Card'!E71) -> 0 | N71: =$F71*N('Rate Card'!G71) -> 0
A72: x | B72: ='Rate Card'!A72 -> PM | C72: ='Rate Card'!B72 -> Project Plan Development | D72: ='Rate Card'!C72 -> Service | E72: ='Rate Card'!D72 -> Fixed | F72: =IF($A72="x",IFERROR(INDEX(DriverQty,MATCH($E72,DriverName,0)),0),0) -> 1 | G72: ='Rate Card'!I72 -> 57000 | I72: =IF($D72="Pass-through",0,MAX(MarginFloor,IF($H72="",MarginLever,$H72))) -> 0.225 | J72: =IF($D72="Pass-through",$G72,IF($I72>=1,$G72,ROUND($G72/(1-$I72),0))) -> 73548 | K72: =$F72*$J72 -> 73548 | L72: =$F72*$G72 -> 57000 | M72: =$F72*N('Rate Card'!E72) -> 40 | N72: =$F72*N('Rate Card'!G72) -> 1
B73: ='Rate Card'!A73 -> PM | C73: ='Rate Card'!B73 -> PMP Development | D73: ='Rate Card'!C73 -> Service | E73: ='Rate Card'!D73 -> Fixed | F73: =IF($A73="x",IFERROR(INDEX(DriverQty,MATCH($E73,DriverName,0)),0),0) -> 0 | G73: ='Rate Card'!I73 -> 54000 | I73: =IF($D73="Pass-through",0,MAX(MarginFloor,IF($H73="",MarginLever,$H73))) -> 0.225 | J73: =IF($D73="Pass-through",$G73,IF($I73>=1,$G73,ROUND($G73/(1-$I73),0))) -> 69677 | K73: =$F73*$J73 -> 0 | L73: =$F73*$G73 -> 0 | M73: =$F73*N('Rate Card'!E73) -> 0 | N73: =$F73*N('Rate Card'!G73) -> 0
B74: ='Rate Card'!A74 -> PM | C74: ='Rate Card'!B74 -> Study Plans | D74: ='Rate Card'!C74 -> Service | E74: ='Rate Card'!D74 -> Fixed | F74: =IF($A74="x",IFERROR(INDEX(DriverQty,MATCH($E74,DriverName,0)),0),0) -> 0 | G74: ='Rate Card'!I74 -> 108000 | I74: =IF($D74="Pass-through",0,MAX(MarginFloor,IF($H74="",MarginLever,$H74))) -> 0.225 | J74: =IF($D74="Pass-through",$G74,IF($I74>=1,$G74,ROUND($G74/(1-$I74),0))) -> 139355 | K74: =$F74*$J74 -> 0 | L74: =$F74*$G74 -> 0 | M74: =$F74*N('Rate Card'!E74) -> 0 | N74: =$F74*N('Rate Card'!G74) -> 0
A75: x | B75: ='Rate Card'!A75 -> PM | C75: ='Rate Card'!B75 -> KO preparation & meeting | D75: ='Rate Card'!C75 -> Service | E75: ='Rate Card'!D75 -> Fixed | F75: =IF($A75="x",IFERROR(INDEX(DriverQty,MATCH($E75,DriverName,0)),0),0) -> 1 | G75: ='Rate Card'!I75 -> 5400 | I75: =IF($D75="Pass-through",0,MAX(MarginFloor,IF($H75="",MarginLever,$H75))) -> 0.225 | J75: =IF($D75="Pass-through",$G75,IF($I75>=1,$G75,ROUND($G75/(1-$I75),0))) -> 6968 | K75: =$F75*$J75 -> 6968 | L75: =$F75*$G75 -> 5400 | M75: =$F75*N('Rate Card'!E75) -> 4 | N75: =$F75*N('Rate Card'!G75) -> 0
B76: ='Rate Card'!A76 -> PM | C76: ='Rate Card'!B76 -> TMF Management (per site) | D76: ='Rate Card'!C76 -> Service | E76: ='Rate Card'!D76 -> Per site | F76: =IF($A76="x",IFERROR(INDEX(DriverQty,MATCH($E76,DriverName,0)),0),0) -> 0 | G76: ='Rate Card'!I76 -> 54000 | I76: =IF($D76="Pass-through",0,MAX(MarginFloor,IF($H76="",MarginLever,$H76))) -> 0.225 | J76: =IF($D76="Pass-through",$G76,IF($I76>=1,$G76,ROUND($G76/(1-$I76),0))) -> 69677 | K76: =$F76*$J76 -> 0 | L76: =$F76*$G76 -> 0 | M76: =$F76*N('Rate Card'!E76) -> 0 | N76: =$F76*N('Rate Card'!G76) -> 0
B77: ='Rate Card'!A77 -> PM | C77: ='Rate Card'!B77 -> Liasioning with Interdepartments on Client Review and Finalization, Data Analysis, Report Finalization, Tech Team Guidance on CRF Deployment, Quality Management and Compliance | D77: ='Rate Card'!C77 -> Service | E77: ='Rate Card'!D77 -> Fixed | F77: =IF($A77="x",IFERROR(INDEX(DriverQty,MATCH($E77,DriverName,0)),0),0) -> 0 | G77: ='Rate Card'!I77 -> 135000 | I77: =IF($D77="Pass-through",0,MAX(MarginFloor,IF($H77="",MarginLever,$H77))) -> 0.225 | J77: =IF($D77="Pass-through",$G77,IF($I77>=1,$G77,ROUND($G77/(1-$I77),0))) -> 174194 | K77: =$F77*$J77 -> 0 | L77: =$F77*$G77 -> 0 | M77: =$F77*N('Rate Card'!E77) -> 0 | N77: =$F77*N('Rate Card'!G77) -> 0
A78: x | B78: ='Rate Card'!A78 -> PM | C78: ='Rate Card'!B78 -> Study Progress Calls (Daily Progress Update and Tracking, PPT, MoM and Internal Update Calls) per site per month | D78: ='Rate Card'!C78 -> Service | E78: ='Rate Card'!D78 -> Per site-month | F78: =IF($A78="x",IFERROR(INDEX(DriverQty,MATCH($E78,DriverName,0)),0),0) -> 60 | G78: ='Rate Card'!I78 -> 5400 | I78: =IF($D78="Pass-through",0,MAX(MarginFloor,IF($H78="",MarginLever,$H78))) -> 0.225 | J78: =IF($D78="Pass-through",$G78,IF($I78>=1,$G78,ROUND($G78/(1-$I78),0))) -> 6968 | K78: =$F78*$J78 -> 418080 | L78: =$F78*$G78 -> 324000 | M78: =$F78*N('Rate Card'!E78) -> 240 | N78: =$F78*N('Rate Card'!G78) -> 0
B79: ='Rate Card'!A79 -> PM | C79: ='Rate Card'!B79 -> Client calls weekly | D79: ='Rate Card'!C79 -> Service | E79: ='Rate Card'!D79 -> Per week | F79: =IF($A79="x",IFERROR(INDEX(DriverQty,MATCH($E79,DriverName,0)),0),0) -> 0 | G79: ='Rate Card'!I79 -> 62700 | I79: =IF($D79="Pass-through",0,MAX(MarginFloor,IF($H79="",MarginLever,$H79))) -> 0.225 | J79: =IF($D79="Pass-through",$G79,IF($I79>=1,$G79,ROUND($G79/(1-$I79),0))) -> 80903 | K79: =$F79*$J79 -> 0 | L79: =$F79*$G79 -> 0 | M79: =$F79*N('Rate Card'!E79) -> 0 | N79: =$F79*N('Rate Card'!G79) -> 0
B80: ='Rate Card'!A80 -> PM | C80: ='Rate Card'!B80 -> Vendor Management | D80: ='Rate Card'!C80 -> Service | E80: ='Rate Card'!D80 -> Fixed | F80: =IF($A80="x",IFERROR(INDEX(DriverQty,MATCH($E80,DriverName,0)),0),0) -> 0 | G80: ='Rate Card'!I80 -> 10800 | I80: =IF($D80="Pass-through",0,MAX(MarginFloor,IF($H80="",MarginLever,$H80))) -> 0.225 | J80: =IF($D80="Pass-through",$G80,IF($I80>=1,$G80,ROUND($G80/(1-$I80),0))) -> 13935 | K80: =$F80*$J80 -> 0 | L80: =$F80*$G80 -> 0 | M80: =$F80*N('Rate Card'!E80) -> 0 | N80: =$F80*N('Rate Card'!G80) -> 0
A81: x | B81: ='Rate Card'!A81 -> PM | C81: ='Rate Card'!B81 -> Project Close-out | D81: ='Rate Card'!C81 -> Service | E81: ='Rate Card'!D81 -> Fixed | F81: =IF($A81="x",IFERROR(INDEX(DriverQty,MATCH($E81,DriverName,0)),0),0) -> 1 | G81: ='Rate Card'!I81 -> 108000 | I81: =IF($D81="Pass-through",0,MAX(MarginFloor,IF($H81="",MarginLever,$H81))) -> 0.225 | J81: =IF($D81="Pass-through",$G81,IF($I81>=1,$G81,ROUND($G81/(1-$I81),0))) -> 139355 | K81: =$F81*$J81 -> 139355 | L81: =$F81*$G81 -> 108000 | M81: =$F81*N('Rate Card'!E81) -> 80 | N81: =$F81*N('Rate Card'!G81) -> 0
B82: ='Rate Card'!A82 -> SM | C82: ='Rate Card'!B82 -> Daily follow-up | D82: ='Rate Card'!C82 -> Service | E82: ='Rate Card'!D82 -> Per site-month | F82: =IF($A82="x",IFERROR(INDEX(DriverQty,MATCH($E82,DriverName,0)),0),0) -> 0 | G82: ='Rate Card'!I82 -> 275 | I82: =IF($D82="Pass-through",0,MAX(MarginFloor,IF($H82="",MarginLever,$H82))) -> 0.225 | J82: =IF($D82="Pass-through",$G82,IF($I82>=1,$G82,ROUND($G82/(1-$I82),0))) -> 355 | K82: =$F82*$J82 -> 0 | L82: =$F82*$G82 -> 0 | M82: =$F82*N('Rate Card'!E82) -> 0 | N82: =$F82*N('Rate Card'!G82) -> 0
B83: ='Rate Card'!A83 -> SM | C83: ='Rate Card'!B83 -> Documentation | D83: ='Rate Card'!C83 -> Service | E83: ='Rate Card'!D83 -> Per site-month | F83: =IF($A83="x",IFERROR(INDEX(DriverQty,MATCH($E83,DriverName,0)),0),0) -> 0 | G83: ='Rate Card'!I83 -> 275 | I83: =IF($D83="Pass-through",0,MAX(MarginFloor,IF($H83="",MarginLever,$H83))) -> 0.225 | J83: =IF($D83="Pass-through",$G83,IF($I83>=1,$G83,ROUND($G83/(1-$I83),0))) -> 355 | K83: =$F83*$J83 -> 0 | L83: =$F83*$G83 -> 0 | M83: =$F83*N('Rate Card'!E83) -> 0 | N83: =$F83*N('Rate Card'!G83) -> 0
B84: ='Rate Card'!A84 -> SM | C84: ='Rate Card'!B84 -> EDC verification | D84: ='Rate Card'!C84 -> Service | E84: ='Rate Card'!D84 -> Per site | F84: =IF($A84="x",IFERROR(INDEX(DriverQty,MATCH($E84,DriverName,0)),0),0) -> 0 | G84: ='Rate Card'!I84 -> 11000 | I84: =IF($D84="Pass-through",0,MAX(MarginFloor,IF($H84="",MarginLever,$H84))) -> 0.225 | J84: =IF($D84="Pass-through",$G84,IF($I84>=1,$G84,ROUND($G84/(1-$I84),0))) -> 14194 | K84: =$F84*$J84 -> 0 | L84: =$F84*$G84 -> 0 | M84: =$F84*N('Rate Card'!E84) -> 0 | N84: =$F84*N('Rate Card'!G84) -> 0
B85: ='Rate Card'!A85 -> SM | C85: ='Rate Card'!B85 -> Query resolutions | D85: ='Rate Card'!C85 -> Service | E85: ='Rate Card'!D85 -> Per site | F85: =IF($A85="x",IFERROR(INDEX(DriverQty,MATCH($E85,DriverName,0)),0),0) -> 0 | G85: ='Rate Card'!I85 -> 8800 | I85: =IF($D85="Pass-through",0,MAX(MarginFloor,IF($H85="",MarginLever,$H85))) -> 0.225 | J85: =IF($D85="Pass-through",$G85,IF($I85>=1,$G85,ROUND($G85/(1-$I85),0))) -> 11355 | K85: =$F85*$J85 -> 0 | L85: =$F85*$G85 -> 0 | M85: =$F85*N('Rate Card'!E85) -> 0 | N85: =$F85*N('Rate Card'!G85) -> 0
B86: ='Rate Card'!A86 -> SM | C86: ='Rate Card'!B86 -> Site re-training | D86: ='Rate Card'!C86 -> Service | E86: ='Rate Card'!D86 -> Per site | F86: =IF($A86="x",IFERROR(INDEX(DriverQty,MATCH($E86,DriverName,0)),0),0) -> 0 | G86: ='Rate Card'!I86 -> 4400 | I86: =IF($D86="Pass-through",0,MAX(MarginFloor,IF($H86="",MarginLever,$H86))) -> 0.225 | J86: =IF($D86="Pass-through",$G86,IF($I86>=1,$G86,ROUND($G86/(1-$I86),0))) -> 5677 | K86: =$F86*$J86 -> 0 | L86: =$F86*$G86 -> 0 | M86: =$F86*N('Rate Card'!E86) -> 0 | N86: =$F86*N('Rate Card'!G86) -> 0
B87: ='Rate Card'!A87 -> SM | C87: ='Rate Card'!B87 -> SIV preparation | D87: ='Rate Card'!C87 -> Service | E87: ='Rate Card'!D87 -> Per site | F87: =IF($A87="x",IFERROR(INDEX(DriverQty,MATCH($E87,DriverName,0)),0),0) -> 0 | G87: ='Rate Card'!I87 -> 22000 | I87: =IF($D87="Pass-through",0,MAX(MarginFloor,IF($H87="",MarginLever,$H87))) -> 0.225 | J87: =IF($D87="Pass-through",$G87,IF($I87>=1,$G87,ROUND($G87/(1-$I87),0))) -> 28387 | K87: =$F87*$J87 -> 0 | L87: =$F87*$G87 -> 0 | M87: =$F87*N('Rate Card'!E87) -> 0 | N87: =$F87*N('Rate Card'!G87) -> 0
B88: ='Rate Card'!A88 -> SM | C88: ='Rate Card'!B88 -> SIV | D88: ='Rate Card'!C88 -> Service | E88: ='Rate Card'!D88 -> Per site | F88: =IF($A88="x",IFERROR(INDEX(DriverQty,MATCH($E88,DriverName,0)),0),0) -> 0 | G88: ='Rate Card'!I88 -> 17600 | I88: =IF($D88="Pass-through",0,MAX(MarginFloor,IF($H88="",MarginLever,$H88))) -> 0.225 | J88: =IF($D88="Pass-through",$G88,IF($I88>=1,$G88,ROUND($G88/(1-$I88),0))) -> 22710 | K88: =$F88*$J88 -> 0 | L88: =$F88*$G88 -> 0 | M88: =$F88*N('Rate Card'!E88) -> 0 | N88: =$F88*N('Rate Card'!G88) -> 0
B89: ='Rate Card'!A89 -> SM | C89: ='Rate Card'!B89 -> SMV preparation | D89: ='Rate Card'!C89 -> Service | E89: ='Rate Card'!D89 -> Per monitoring visit | F89: =IF($A89="x",IFERROR(INDEX(DriverQty,MATCH($E89,DriverName,0)),0),0) -> 0 | G89: ='Rate Card'!I89 -> 8800 | I89: =IF($D89="Pass-through",0,MAX(MarginFloor,IF($H89="",MarginLever,$H89))) -> 0.225 | J89: =IF($D89="Pass-through",$G89,IF($I89>=1,$G89,ROUND($G89/(1-$I89),0))) -> 11355 | K89: =$F89*$J89 -> 0 | L89: =$F89*$G89 -> 0 | M89: =$F89*N('Rate Card'!E89) -> 0 | N89: =$F89*N('Rate Card'!G89) -> 0
B90: ='Rate Card'!A90 -> SM | C90: ='Rate Card'!B90 -> SMV | D90: ='Rate Card'!C90 -> Service | E90: ='Rate Card'!D90 -> Per monitoring visit | F90: =IF($A90="x",IFERROR(INDEX(DriverQty,MATCH($E90,DriverName,0)),0),0) -> 0 | G90: ='Rate Card'!I90 -> 17600 | I90: =IF($D90="Pass-through",0,MAX(MarginFloor,IF($H90="",MarginLever,$H90))) -> 0.225 | J90: =IF($D90="Pass-through",$G90,IF($I90>=1,$G90,ROUND($G90/(1-$I90),0))) -> 22710 | K90: =$F90*$J90 -> 0 | L90: =$F90*$G90 -> 0 | M90: =$F90*N('Rate Card'!E90) -> 0 | N90: =$F90*N('Rate Card'!G90) -> 0
B91: ='Rate Card'!A91 -> SM | C91: ='Rate Card'!B91 -> SCV Preparation | D91: ='Rate Card'!C91 -> Service | E91: ='Rate Card'!D91 -> Per site | F91: =IF($A91="x",IFERROR(INDEX(DriverQty,MATCH($E91,DriverName,0)),0),0) -> 0 | G91: ='Rate Card'!I91 -> 17600 | I91: =IF($D91="Pass-through",0,MAX(MarginFloor,IF($H91="",MarginLever,$H91))) -> 0.225 | J91: =IF($D91="Pass-through",$G91,IF($I91>=1,$G91,ROUND($G91/(1-$I91),0))) -> 22710 | K91: =$F91*$J91 -> 0 | L91: =$F91*$G91 -> 0 | M91: =$F91*N('Rate Card'!E91) -> 0 | N91: =$F91*N('Rate Card'!G91) -> 0
B92: ='Rate Card'!A92 -> SM | C92: ='Rate Card'!B92 -> SCV | D92: ='Rate Card'!C92 -> Service | E92: ='Rate Card'!D92 -> Per site | F92: =IF($A92="x",IFERROR(INDEX(DriverQty,MATCH($E92,DriverName,0)),0),0) -> 0 | G92: ='Rate Card'!I92 -> 17600 | I92: =IF($D92="Pass-through",0,MAX(MarginFloor,IF($H92="",MarginLever,$H92))) -> 0.225 | J92: =IF($D92="Pass-through",$G92,IF($I92>=1,$G92,ROUND($G92/(1-$I92),0))) -> 22710 | K92: =$F92*$J92 -> 0 | L92: =$F92*$G92 -> 0 | M92: =$F92*N('Rate Card'!E92) -> 0 | N92: =$F92*N('Rate Card'!G92) -> 0
B93: ='Rate Card'!A93 -> SM | C93: ='Rate Card'!B93 -> Local travel for visits | D93: ='Rate Card'!C93 -> Service | E93: ='Rate Card'!D93 -> Per monitoring visit | F93: =IF($A93="x",IFERROR(INDEX(DriverQty,MATCH($E93,DriverName,0)),0),0) -> 0 | G93: ='Rate Card'!I93 -> 5500 | I93: =IF($D93="Pass-through",0,MAX(MarginFloor,IF($H93="",MarginLever,$H93))) -> 0.225 | J93: =IF($D93="Pass-through",$G93,IF($I93>=1,$G93,ROUND($G93/(1-$I93),0))) -> 7097 | K93: =$F93*$J93 -> 0 | L93: =$F93*$G93 -> 0 | M93: =$F93*N('Rate Card'!E93) -> 0 | N93: =$F93*N('Rate Card'!G93) -> 0
B94: ='Rate Card'!A94 -> SM | C94: ='Rate Card'!B94 -> Out-station travel for visits | D94: ='Rate Card'!C94 -> Service | E94: ='Rate Card'!D94 -> Per monitoring visit | F94: =IF($A94="x",IFERROR(INDEX(DriverQty,MATCH($E94,DriverName,0)),0),0) -> 0 | G94: ='Rate Card'!I94 -> 15400 | I94: =IF($D94="Pass-through",0,MAX(MarginFloor,IF($H94="",MarginLever,$H94))) -> 0.225 | J94: =IF($D94="Pass-through",$G94,IF($I94>=1,$G94,ROUND($G94/(1-$I94),0))) -> 19871 | K94: =$F94*$J94 -> 0 | L94: =$F94*$G94 -> 0 | M94: =$F94*N('Rate Card'!E94) -> 0 | N94: =$F94*N('Rate Card'!G94) -> 0
A95: x | B95: ='Rate Card'!A95 -> EC | C95: ='Rate Card'!B95 -> Registration | D95: ='Rate Card'!C95 -> Service | E95: ='Rate Card'!D95 -> Fixed | F95: =IF($A95="x",IFERROR(INDEX(DriverQty,MATCH($E95,DriverName,0)),0),0) -> 1 | G95: ='Rate Card'!I95 -> 12000 | I95: =IF($D95="Pass-through",0,MAX(MarginFloor,IF($H95="",MarginLever,$H95))) -> 0.225 | J95: =IF($D95="Pass-through",$G95,IF($I95>=1,$G95,ROUND($G95/(1-$I95),0))) -> 15484 | K95: =$F95*$J95 -> 15484 | L95: =$F95*$G95 -> 12000 | M95: =$F95*N('Rate Card'!E95) -> 10 | N95: =$F95*N('Rate Card'!G95) -> 0
A96: x | B96: ='Rate Card'!A96 -> EC | C96: ='Rate Card'!B96 -> CTRI submission | D96: ='Rate Card'!C96 -> Service | E96: ='Rate Card'!D96 -> Fixed | F96: =IF($A96="x",IFERROR(INDEX(DriverQty,MATCH($E96,DriverName,0)),0),0) -> 1 | G96: ='Rate Card'!I96 -> 12000 | I96: =IF($D96="Pass-through",0,MAX(MarginFloor,IF($H96="",MarginLever,$H96))) -> 0.225 | J96: =IF($D96="Pass-through",$G96,IF($I96>=1,$G96,ROUND($G96/(1-$I96),0))) -> 15484 | K96: =$F96*$J96 -> 15484 | L96: =$F96*$G96 -> 12000 | M96: =$F96*N('Rate Card'!E96) -> 10 | N96: =$F96*N('Rate Card'!G96) -> 0
B97: ='Rate Card'!A97 -> EC | C97: ='Rate Card'!B97 -> CTRI query resolution | D97: ='Rate Card'!C97 -> Service | E97: ='Rate Card'!D97 -> Fixed | F97: =IF($A97="x",IFERROR(INDEX(DriverQty,MATCH($E97,DriverName,0)),0),0) -> 0 | G97: ='Rate Card'!I97 -> 6000 | I97: =IF($D97="Pass-through",0,MAX(MarginFloor,IF($H97="",MarginLever,$H97))) -> 0.225 | J97: =IF($D97="Pass-through",$G97,IF($I97>=1,$G97,ROUND($G97/(1-$I97),0))) -> 7742 | K97: =$F97*$J97 -> 0 | L97: =$F97*$G97 -> 0 | M97: =$F97*N('Rate Card'!E97) -> 0 | N97: =$F97*N('Rate Card'!G97) -> 0
B98: ='Rate Card'!A98 -> EC | C98: ='Rate Card'!B98 -> Client Communications | D98: ='Rate Card'!C98 -> Service | E98: ='Rate Card'!D98 -> Per month | F98: =IF($A98="x",IFERROR(INDEX(DriverQty,MATCH($E98,DriverName,0)),0),0) -> 0 | G98: ='Rate Card'!I98 -> 6000 | I98: =IF($D98="Pass-through",0,MAX(MarginFloor,IF($H98="",MarginLever,$H98))) -> 0.225 | J98: =IF($D98="Pass-through",$G98,IF($I98>=1,$G98,ROUND($G98/(1-$I98),0))) -> 7742 | K98: =$F98*$J98 -> 0 | L98: =$F98*$G98 -> 0 | M98: =$F98*N('Rate Card'!E98) -> 0 | N98: =$F98*N('Rate Card'!G98) -> 0
B99: ='Rate Card'!A99 -> EC | C99: ='Rate Card'!B99 -> Coordination with PM | D99: ='Rate Card'!C99 -> Service | E99: ='Rate Card'!D99 -> Per month | F99: =IF($A99="x",IFERROR(INDEX(DriverQty,MATCH($E99,DriverName,0)),0),0) -> 0 | G99: ='Rate Card'!I99 -> 12000 | I99: =IF($D99="Pass-through",0,MAX(MarginFloor,IF($H99="",MarginLever,$H99))) -> 0.225 | J99: =IF($D99="Pass-through",$G99,IF($I99>=1,$G99,ROUND($G99/(1-$I99),0))) -> 15484 | K99: =$F99*$J99 -> 0 | L99: =$F99*$G99 -> 0 | M99: =$F99*N('Rate Card'!E99) -> 0 | N99: =$F99*N('Rate Card'!G99) -> 0
B100: ='Rate Card'!A100 -> EC | C100: ='Rate Card'!B100 -> CTRI Updates | D100: ='Rate Card'!C100 -> Service | E100: ='Rate Card'!D100 -> Fixed | F100: =IF($A100="x",IFERROR(INDEX(DriverQty,MATCH($E100,DriverName,0)),0),0) -> 0 | G100: ='Rate Card'!I100 -> 6000 | I100: =IF($D100="Pass-through",0,MAX(MarginFloor,IF($H100="",MarginLever,$H100))) -> 0.225 | J100: =IF($D100="Pass-through",$G100,IF($I100>=1,$G100,ROUND($G100/(1-$I100),0))) -> 7742 | K100: =$F100*$J100 -> 0 | L100: =$F100*$G100 -> 0 | M100: =$F100*N('Rate Card'!E100) -> 0 | N100: =$F100*N('Rate Card'!G100) -> 0
...
